{
  "source": "https://www.ipc-computer.eu/laptop-spare-parts/displays",
  "siteCount": 6873,
  "maxPage": 688,
  "pagesScanned": 688,
  "productCards": 6863,
  "uniqueProducts": 6863,
  "eolCount": 223,
  "eol": [
    {
      "title": "935442-J92 HP IPS Display FHD matt 60Hz",
      "url": "https://www.ipc-computer.eu/laptop-spare-parts/displays/display-935442-j92-103095296",
      "availability": "Out of stock EOL (End of Life) What does EOL mean?",
      "stock": "Out of stock",
      "isEol": true,
      "page": 666,
      "pageUrl": "https://www.ipc-computer.eu/laptop-spare-parts/displays?page=666"
    },
    {
      "title": "B156HTN06.1 H/W:2A F/W:1 Asus TN Display FHD glossy 60Hz",
      "url": "https://www.ipc-computer.eu/laptop-spare-parts/displays/display-b156htn06.1-h-w-2a-f-w-1-62345683",
      "availability": "Out of stock EOL (End of Life) What does EOL mean?",
      "stock": "Out of stock",
      "isEol": true,
      "page": 666,
      "pageUrl": "https://www.ipc-computer.eu/laptop-spare-parts/displays?page=666"
    },
    {
      "title": "KL.1600E.001 Acer original IPS Display WQXGA matt 165Hz",
      "url": "https://www.ipc-computer.eu/laptop-spare-parts/displays/display-kl.1600e.001-98031274",
      "availability": "Out of stock EOL (End of Life) What does EOL mean?",
      "stock": "Out of stock",
      "isEol": true,
      "page": 666,
      "pageUrl": "https://www.ipc-computer.eu/laptop-spare-parts/displays?page=666"
    },
    {
      "title": "KL.1600W.001 Acer original IPS Display WQXGA matt 165Hz",
      "url": "https://www.ipc-computer.eu/laptop-spare-parts/displays/display-kl.1600w.001-98031276",
      "availability": "Out of stock EOL (End of Life) What does EOL mean?",
      "stock": "Out of stock",
      "isEol": true,
      "page": 666,
      "pageUrl": "https://www.ipc-computer.eu/laptop-spare-parts/displays?page=666"
    },
    {
      "title": "KL1600E001 Acer original IPS Display WQXGA matt 165Hz",
      "url": "https://www.ipc-computer.eu/laptop-spare-parts/displays/display-kl1600e001-98031277",
      "availability": "Out of stock EOL (End of Life) What does EOL mean?",
      "stock": "Out of stock",
      "isEol": true,
      "page": 666,
      "pageUrl": "https://www.ipc-computer.eu/laptop-spare-parts/displays?page=666"
    },
    {
      "title": "KL1600W001 Acer original IPS Display WQXGA matt 165Hz",
      "url": "https://www.ipc-computer.eu/laptop-spare-parts/displays/display-kl1600w001-98031279",
      "availability": "Out of stock EOL (End of Life) What does EOL mean?",
      "stock": "Out of stock",
      "isEol": true,
      "page": 666,
      "pageUrl": "https://www.ipc-computer.eu/laptop-spare-parts/displays?page=666"
    },
    {
      "title": "MV238FHM-N20 A85G LF BOE IPS Display FHD matt 75Hz",
      "url": "https://www.ipc-computer.eu/laptop-spare-parts/displays/display-mv238fhm-n20-a85g-lf-101994786",
      "availability": "Out of stock EOL (End of Life) What does EOL mean?",
      "stock": "Out of stock",
      "isEol": true,
      "page": 666,
      "pageUrl": "https://www.ipc-computer.eu/laptop-spare-parts/displays?page=666"
    },
    {
      "title": "N173HHE-G32 Innolux IPS Display matt 120Hz (120Hz / 40-Pin eDP)",
      "url": "https://www.ipc-computer.eu/laptop-spare-parts/displays/display-n173hhe-g32-97361932",
      "availability": "Out of stock EOL (End of Life) What does EOL mean?",
      "stock": "Out of stock",
      "isEol": true,
      "page": 666,
      "pageUrl": "https://www.ipc-computer.eu/laptop-spare-parts/displays?page=666"
    },
    {
      "title": "S1J-JE0A031-B51 MSI original IPS Display FHD matt 144Hz",
      "url": "https://www.ipc-computer.eu/laptop-spare-parts/displays/display-s1j-je0a031-b51-150250583",
      "availability": "Out of stock EOL (End of Life) What does EOL mean?",
      "stock": "Out of stock",
      "isEol": true,
      "page": 666,
      "pageUrl": "https://www.ipc-computer.eu/laptop-spare-parts/displays?page=666"
    },
    {
      "title": "S1J-JE0A316-B51 MSI original IPS Display FHD matt 144Hz",
      "url": "https://www.ipc-computer.eu/laptop-spare-parts/displays/display-s1j-je0a316-b51-150250584",
      "availability": "Out of stock EOL (End of Life) What does EOL mean?",
      "stock": "Out of stock",
      "isEol": true,
      "page": 666,
      "pageUrl": "https://www.ipc-computer.eu/laptop-spare-parts/displays?page=666"
    },
    {
      "title": "18010-13320100 Asus original Display matt",
      "url": "https://www.ipc-computer.eu/laptop-spare-parts/displays/display-18010-13320100-89090887",
      "availability": "Out of stock EOL (End of Life) What does EOL mean?",
      "stock": "Out of stock",
      "isEol": true,
      "page": 667,
      "pageUrl": "https://www.ipc-computer.eu/laptop-spare-parts/displays?page=667"
    },
    {
      "title": "18010-15611900 Asus original IPS Display FHD matt 60Hz",
      "url": "https://www.ipc-computer.eu/laptop-spare-parts/displays/display-18010-15611900-78890360",
      "availability": "Out of stock EOL (End of Life) What does EOL mean?",
      "stock": "Out of stock",
      "isEol": true,
      "page": 667,
      "pageUrl": "https://www.ipc-computer.eu/laptop-spare-parts/displays?page=667"
    },
    {
      "title": "413000021175 Mitac TN Display WXGA matt 60Hz",
      "url": "https://www.ipc-computer.eu/laptop-spare-parts/displays/display-413000021175-18903853/nup",
      "availability": "Out of stock EOL (End of Life) What does EOL mean?",
      "stock": "Out of stock",
      "isEol": true,
      "page": 667,
      "pageUrl": "https://www.ipc-computer.eu/laptop-spare-parts/displays?page=667"
    },
    {
      "title": "6-50-L8262-G00 Clevo TN Display WXGA matt 60Hz",
      "url": "https://www.ipc-computer.eu/laptop-spare-parts/displays/display-6-50-l8262-g00-27499490/nup",
      "availability": "Out of stock EOL (End of Life) What does EOL mean?",
      "stock": "Out of stock",
      "isEol": true,
      "page": 667,
      "pageUrl": "https://www.ipc-computer.eu/laptop-spare-parts/displays?page=667"
    },
    {
      "title": "70421600000 Packard Bell TN Display WXGA matt 60Hz",
      "url": "https://www.ipc-computer.eu/laptop-spare-parts/displays/display-70421600000-18909617/nup",
      "availability": "Out of stock EOL (End of Life) What does EOL mean?",
      "stock": "Out of stock",
      "isEol": true,
      "page": 667,
      "pageUrl": "https://www.ipc-computer.eu/laptop-spare-parts/displays?page=667"
    },
    {
      "title": "764623-001 HP TN Display FHD matt 60Hz",
      "url": "https://www.ipc-computer.eu/laptop-spare-parts/displays/display-764623-001-101298246",
      "availability": "Out of stock EOL (End of Life) What does EOL mean?",
      "stock": "Out of stock",
      "isEol": true,
      "page": 667,
      "pageUrl": "https://www.ipc-computer.eu/laptop-spare-parts/displays?page=667"
    },
    {
      "title": "CP519469-XX Fujitsu TN Display HD+ matt 60Hz",
      "url": "https://www.ipc-computer.eu/laptop-spare-parts/displays/display-cp519469-xx-32731138/nup",
      "availability": "Out of stock EOL (End of Life) What does EOL mean?",
      "stock": "Out of stock",
      "isEol": true,
      "page": 667,
      "pageUrl": "https://www.ipc-computer.eu/laptop-spare-parts/displays?page=667"
    },
    {
      "title": "FSP:840N00002 Fujitsu TN Display WXGA matt 60Hz",
      "url": "https://www.ipc-computer.eu/laptop-spare-parts/displays/display-fsp-840n00002-18922579/nup",
      "availability": "Out of stock EOL (End of Life) What does EOL mean?",
      "stock": "Out of stock",
      "isEol": true,
      "page": 667,
      "pageUrl": "https://www.ipc-computer.eu/laptop-spare-parts/displays?page=667"
    },
    {
      "title": "N156HGE-LG1 Innolux TN Display FHD matt 60Hz",
      "url": "https://www.ipc-computer.eu/laptop-spare-parts/displays/display-n156hge-lg1-101298272",
      "availability": "Out of stock EOL (End of Life) What does EOL mean?",
      "stock": "Out of stock",
      "isEol": true,
      "page": 667,
      "pageUrl": "https://www.ipc-computer.eu/laptop-spare-parts/displays?page=667"
    },
    {
      "title": "UWL:72-115261-00 Fujitsu TN Display WXGA matt 60Hz",
      "url": "https://www.ipc-computer.eu/laptop-spare-parts/displays/display-uwl-72-115261-00-18938973/nup",
      "availability": "Out of stock EOL (End of Life) What does EOL mean?",
      "stock": "Out of stock",
      "isEol": true,
      "page": 667,
      "pageUrl": "https://www.ipc-computer.eu/laptop-spare-parts/displays?page=667"
    },
    {
      "title": "18010-15612100 Asus original TN Display HD matt 60Hz",
      "url": "https://www.ipc-computer.eu/laptop-spare-parts/displays/display-18010-15612100-25871005/nup",
      "availability": "Out of stock EOL (End of Life) What does EOL mean?",
      "stock": "Out of stock",
      "isEol": true,
      "page": 668,
      "pageUrl": "https://www.ipc-computer.eu/laptop-spare-parts/displays?page=668"
    },
    {
      "title": "18010-15650400 Asus original IPS Display FHD matt 60Hz",
      "url": "https://www.ipc-computer.eu/laptop-spare-parts/displays/display-18010-15650400-78890371",
      "availability": "Out of stock EOL (End of Life) What does EOL mean?",
      "stock": "Out of stock",
      "isEol": true,
      "page": 668,
      "pageUrl": "https://www.ipc-computer.eu/laptop-spare-parts/displays?page=668"
    },
    {
      "title": "18010-17330200 Asus original IPS Display FHD matt 60Hz",
      "url": "https://www.ipc-computer.eu/laptop-spare-parts/displays/display-18010-17330200-144661738",
      "availability": "Out of stock EOL (End of Life) What does EOL mean?",
      "stock": "Out of stock",
      "isEol": true,
      "page": 668,
      "pageUrl": "https://www.ipc-computer.eu/laptop-spare-parts/displays?page=668"
    },
    {
      "title": "18G241560010Q Asus original TN Display HD glossy 60Hz",
      "url": "https://www.ipc-computer.eu/laptop-spare-parts/displays/display-18g241560010q-144661826",
      "availability": "Out of stock EOL (End of Life) What does EOL mean?",
      "stock": "Out of stock",
      "isEol": true,
      "page": 668,
      "pageUrl": "https://www.ipc-computer.eu/laptop-spare-parts/displays?page=668"
    },
    {
      "title": "B156XW03 V.0 HW0A AU Optronics TN Display HD glossy 60Hz",
      "url": "https://www.ipc-computer.eu/laptop-spare-parts/displays/display-b156xw03-v.0-hw0a-144665102",
      "availability": "Out of stock EOL (End of Life) What does EOL mean?",
      "stock": "Out of stock",
      "isEol": true,
      "page": 668,
      "pageUrl": "https://www.ipc-computer.eu/laptop-spare-parts/displays?page=668"
    },
    {
      "title": "B156XW03 V.0 HW1A AU Optronics TN Display HD glossy 60Hz",
      "url": "https://www.ipc-computer.eu/laptop-spare-parts/displays/display-b156xw03-v.0-hw1a-144665103",
      "availability": "Out of stock EOL (End of Life) What does EOL mean?",
      "stock": "Out of stock",
      "isEol": true,
      "page": 668,
      "pageUrl": "https://www.ipc-computer.eu/laptop-spare-parts/displays?page=668"
    },
    {
      "title": "B173ZAN01.0 HW:2A AU Optronics IPS Display UHD matt 60Hz",
      "url": "https://www.ipc-computer.eu/laptop-spare-parts/displays/display-b173zan01.0-hw-2a-46182101",
      "availability": "Out of stock EOL (End of Life) What does EOL mean?",
      "stock": "Out of stock",
      "isEol": true,
      "page": 668,
      "pageUrl": "https://www.ipc-computer.eu/laptop-spare-parts/displays?page=668"
    },
    {
      "title": "KL.17305.006 Acer IPS Display UHD matt 60Hz",
      "url": "https://www.ipc-computer.eu/laptop-spare-parts/displays/display-kl.17305.006-53331098",
      "availability": "Out of stock EOL (End of Life) What does EOL mean?",
      "stock": "Out of stock",
      "isEol": true,
      "page": 668,
      "pageUrl": "https://www.ipc-computer.eu/laptop-spare-parts/displays?page=668"
    },
    {
      "title": "MSC156H40-087G MicroScreen TN Display HD glossy 60Hz",
      "url": "https://www.ipc-computer.eu/laptop-spare-parts/displays/display-msc156h40-087g-144667461",
      "availability": "Out of stock EOL (End of Life) What does EOL mean?",
      "stock": "Out of stock",
      "isEol": true,
      "page": 668,
      "pageUrl": "https://www.ipc-computer.eu/laptop-spare-parts/displays?page=668"
    },
    {
      "title": "N173DSE-G31/B4 Innolux IPS Display UHD matt 60Hz",
      "url": "https://www.ipc-computer.eu/laptop-spare-parts/displays/display-n173dse-g31-b4-46182139",
      "availability": "Out of stock EOL (End of Life) What does EOL mean?",
      "stock": "Out of stock",
      "isEol": true,
      "page": 668,
      "pageUrl": "https://www.ipc-computer.eu/laptop-spare-parts/displays?page=668"
    },
    {
      "title": "18010-15671000 Asus original TN Display FHD matt 120Hz",
      "url": "https://www.ipc-computer.eu/laptop-spare-parts/displays/display-18010-15671000-53438336/nup",
      "availability": "Out of stock EOL (End of Life) What does EOL mean?",
      "stock": "Out of stock",
      "isEol": true,
      "page": 669,
      "pageUrl": "https://www.ipc-computer.eu/laptop-spare-parts/displays?page=669"
    },
    {
      "title": "18010-17321200 Asus IPS Display UHD matt 60Hz",
      "url": "https://www.ipc-computer.eu/laptop-spare-parts/displays/display-18010-17321200-92355115",
      "availability": "Out of stock EOL (End of Life) What does EOL mean?",
      "stock": "Out of stock",
      "isEol": true,
      "page": 669,
      "pageUrl": "https://www.ipc-computer.eu/laptop-spare-parts/displays?page=669"
    },
    {
      "title": "KL.1350E.001 Acer original IPS Display QHD glossy 60Hz",
      "url": "https://www.ipc-computer.eu/laptop-spare-parts/displays/display-kl.1350e.001-73871774",
      "availability": "Out of stock EOL (End of Life) What does EOL mean?",
      "stock": "Out of stock",
      "isEol": true,
      "page": 669,
      "pageUrl": "https://www.ipc-computer.eu/laptop-spare-parts/displays?page=669"
    },
    {
      "title": "KL.23808.015 Acer original IPS Display FHD matt 75Hz",
      "url": "https://www.ipc-computer.eu/laptop-spare-parts/displays/display-kl.23808.015-99868662",
      "availability": "Out of stock EOL (End of Life) What does EOL mean?",
      "stock": "Out of stock",
      "isEol": true,
      "page": 669,
      "pageUrl": "https://www.ipc-computer.eu/laptop-spare-parts/displays?page=669"
    },
    {
      "title": "KL.2380E.009 Acer original IPS Display FHD matt 75Hz",
      "url": "https://www.ipc-computer.eu/laptop-spare-parts/displays/display-kl.2380e.009-99868663",
      "availability": "Out of stock EOL (End of Life) What does EOL mean?",
      "stock": "Out of stock",
      "isEol": true,
      "page": 669,
      "pageUrl": "https://www.ipc-computer.eu/laptop-spare-parts/displays?page=669"
    },
    {
      "title": "KL.2380E.014 Acer original IPS Display FHD matt 75Hz",
      "url": "https://www.ipc-computer.eu/laptop-spare-parts/displays/display-kl.2380e.014-99868665",
      "availability": "Out of stock EOL (End of Life) What does EOL mean?",
      "stock": "Out of stock",
      "isEol": true,
      "page": 669,
      "pageUrl": "https://www.ipc-computer.eu/laptop-spare-parts/displays?page=669"
    },
    {
      "title": "KL.2380E.015 Acer original IPS Display FHD matt 75Hz",
      "url": "https://www.ipc-computer.eu/laptop-spare-parts/displays/display-kl.2380e.015-74119264",
      "availability": "Out of stock EOL (End of Life) What does EOL mean?",
      "stock": "Out of stock",
      "isEol": true,
      "page": 669,
      "pageUrl": "https://www.ipc-computer.eu/laptop-spare-parts/displays?page=669"
    },
    {
      "title": "KL17308002 Acer original Display HD+ glossy",
      "url": "https://www.ipc-computer.eu/laptop-spare-parts/displays/display-kl17308002-52056085",
      "availability": "Out of stock EOL (End of Life) What does EOL mean?",
      "stock": "Out of stock",
      "isEol": true,
      "page": 669,
      "pageUrl": "https://www.ipc-computer.eu/laptop-spare-parts/displays?page=669"
    },
    {
      "title": "N173DSE-G31 C2 Innolux IPS Display UHD matt 60Hz",
      "url": "https://www.ipc-computer.eu/laptop-spare-parts/displays/display-n173dse-g31-c2-79456244",
      "availability": "Out of stock EOL (End of Life) What does EOL mean?",
      "stock": "Out of stock",
      "isEol": true,
      "page": 669,
      "pageUrl": "https://www.ipc-computer.eu/laptop-spare-parts/displays?page=669"
    },
    {
      "title": "SD10Q75578 Acer IPS Display FHD matt 75Hz",
      "url": "https://www.ipc-computer.eu/laptop-spare-parts/displays/display-sd10q75578-74119304",
      "availability": "Out of stock EOL (End of Life) What does EOL mean?",
      "stock": "Out of stock",
      "isEol": true,
      "page": 669,
      "pageUrl": "https://www.ipc-computer.eu/laptop-spare-parts/displays?page=669"
    },
    {
      "title": "18010-14052100 Asus original IPS Display FHD matt 60Hz",
      "url": "https://www.ipc-computer.eu/laptop-spare-parts/displays/display-18010-14052100-73768379/nup",
      "availability": "Out of stock EOL (End of Life) What does EOL mean?",
      "stock": "Out of stock",
      "isEol": true,
      "page": 670,
      "pageUrl": "https://www.ipc-computer.eu/laptop-spare-parts/displays?page=670"
    },
    {
      "title": "18010-15604500 Asus original TN Display HD glossy 60Hz",
      "url": "https://www.ipc-computer.eu/laptop-spare-parts/displays/display-18010-15604500-144661709",
      "availability": "Out of stock EOL (End of Life) What does EOL mean?",
      "stock": "Out of stock",
      "isEol": true,
      "page": 670,
      "pageUrl": "https://www.ipc-computer.eu/laptop-spare-parts/displays?page=670"
    },
    {
      "title": "18010-17323200 Asus IPS Display FHD matt 120Hz",
      "url": "https://www.ipc-computer.eu/laptop-spare-parts/displays/display-18010-17323200-97640591",
      "availability": "Out of stock EOL (End of Life) What does EOL mean?",
      "stock": "Out of stock",
      "isEol": true,
      "page": 670,
      "pageUrl": "https://www.ipc-computer.eu/laptop-spare-parts/displays?page=670"
    },
    {
      "title": "18010-28000600 Asus original TN Display UHD matt 60Hz",
      "url": "https://www.ipc-computer.eu/laptop-spare-parts/displays/display-18010-28000600-73682559",
      "availability": "Out of stock EOL (End of Life) What does EOL mean?",
      "stock": "Out of stock",
      "isEol": true,
      "page": 670,
      "pageUrl": "https://www.ipc-computer.eu/laptop-spare-parts/displays?page=670"
    },
    {
      "title": "NE135FBM-N41 V8.0 BOE IPS Display QHD glossy 60Hz",
      "url": "https://www.ipc-computer.eu/laptop-spare-parts/displays/display-ne135fbm-n41-v8.0-89129389",
      "availability": "Out of stock EOL (End of Life) What does EOL mean?",
      "stock": "Out of stock",
      "isEol": true,
      "page": 670,
      "pageUrl": "https://www.ipc-computer.eu/laptop-spare-parts/displays?page=670"
    },
    {
      "title": "NT173WDM-N24 V8.0 BOE TN Display HD+ matt 60Hz",
      "url": "https://www.ipc-computer.eu/laptop-spare-parts/displays/display-nt173wdm-n24-v8.0-73744029/nup",
      "availability": "Out of stock EOL (End of Life) What does EOL mean?",
      "stock": "Out of stock",
      "isEol": true,
      "page": 670,
      "pageUrl": "https://www.ipc-computer.eu/laptop-spare-parts/displays?page=670"
    },
    {
      "title": "S1J-6E0A056-L47 MSI original IPS Display FHD matt 144Hz",
      "url": "https://www.ipc-computer.eu/laptop-spare-parts/displays/display-s1j-6e0a056-l47-85112027",
      "availability": "Out of stock EOL (End of Life) What does EOL mean?",
      "stock": "Out of stock",
      "isEol": true,
      "page": 670,
      "pageUrl": "https://www.ipc-computer.eu/laptop-spare-parts/displays?page=670"
    },
    {
      "title": "S1J-7E0A026-A90 MSI original IPS Display FHD matt 60Hz",
      "url": "https://www.ipc-computer.eu/laptop-spare-parts/displays/display-s1j-7e0a026-a90-79967285",
      "availability": "Out of stock EOL (End of Life) What does EOL mean?",
      "stock": "Out of stock",
      "isEol": true,
      "page": 670,
      "pageUrl": "https://www.ipc-computer.eu/laptop-spare-parts/displays?page=670"
    },
    {
      "title": "S1J-7E0A038-A90 MSI original IPS Display FHD matt 144Hz",
      "url": "https://www.ipc-computer.eu/laptop-spare-parts/displays/display-s1j-7e0a038-a90-101301237",
      "availability": "Out of stock EOL (End of Life) What does EOL mean?",
      "stock": "Out of stock",
      "isEol": true,
      "page": 670,
      "pageUrl": "https://www.ipc-computer.eu/laptop-spare-parts/displays?page=670"
    },
    {
      "title": "S1J-7F1A001-A90 MSI original IPS Display FHD matt 120Hz",
      "url": "https://www.ipc-computer.eu/laptop-spare-parts/displays/display-s1j-7f1a001-a90-97640836",
      "availability": "Out of stock EOL (End of Life) What does EOL mean?",
      "stock": "Out of stock",
      "isEol": true,
      "page": 670,
      "pageUrl": "https://www.ipc-computer.eu/laptop-spare-parts/displays?page=670"
    },
    {
      "title": "18010-14003000 Asus original IPS Display FHD matt 60Hz",
      "url": "https://www.ipc-computer.eu/laptop-spare-parts/displays/display-18010-14003000-101303360",
      "availability": "Out of stock EOL (End of Life) What does EOL mean?",
      "stock": "Out of stock",
      "isEol": true,
      "page": 671,
      "pageUrl": "https://www.ipc-computer.eu/laptop-spare-parts/displays?page=671"
    },
    {
      "title": "18010-14004900 Asus original IPS Display FHD matt 60Hz",
      "url": "https://www.ipc-computer.eu/laptop-spare-parts/displays/display-18010-14004900-101303361",
      "availability": "Out of stock EOL (End of Life) What does EOL mean?",
      "stock": "Out of stock",
      "isEol": true,
      "page": 671,
      "pageUrl": "https://www.ipc-computer.eu/laptop-spare-parts/displays?page=671"
    },
    {
      "title": "18010-15605600 Asus original TN Display HD matt 60Hz",
      "url": "https://www.ipc-computer.eu/laptop-spare-parts/displays/display-18010-15605600-144661712",
      "availability": "Out of stock EOL (End of Life) What does EOL mean?",
      "stock": "Out of stock",
      "isEol": true,
      "page": 671,
      "pageUrl": "https://www.ipc-computer.eu/laptop-spare-parts/displays?page=671"
    },
    {
      "title": "18010-17311400 Asus original TN Display HD+ matt 60Hz",
      "url": "https://www.ipc-computer.eu/laptop-spare-parts/displays/display-18010-17311400-76023070",
      "availability": "Out of stock EOL (End of Life) What does EOL mean?",
      "stock": "Out of stock",
      "isEol": true,
      "page": 671,
      "pageUrl": "https://www.ipc-computer.eu/laptop-spare-parts/displays?page=671"
    },
    {
      "title": "18010-17311700 Asus original TN Display HD+ matt 60Hz",
      "url": "https://www.ipc-computer.eu/laptop-spare-parts/displays/display-18010-17311700-95652178",
      "availability": "Out of stock EOL (End of Life) What does EOL mean?",
      "stock": "Out of stock",
      "isEol": true,
      "page": 671,
      "pageUrl": "https://www.ipc-computer.eu/laptop-spare-parts/displays?page=671"
    },
    {
      "title": "90NR03I2-R20011 Asus original IPS Display FHD matt 60Hz",
      "url": "https://www.ipc-computer.eu/laptop-spare-parts/displays/display-90nr03i2-r20011-77593690",
      "availability": "Out of stock EOL (End of Life) What does EOL mean?",
      "stock": "Out of stock",
      "isEol": true,
      "page": 671,
      "pageUrl": "https://www.ipc-computer.eu/laptop-spare-parts/displays?page=671"
    },
    {
      "title": "B156HAK02.1 HP original touch IPS Display FHD glossy 60Hz",
      "url": "https://www.ipc-computer.eu/laptop-spare-parts/displays/display-b156hak02.1-100624808",
      "availability": "Out of stock EOL (End of Life) What does EOL mean?",
      "stock": "Out of stock",
      "isEol": true,
      "page": 671,
      "pageUrl": "https://www.ipc-computer.eu/laptop-spare-parts/displays?page=671"
    },
    {
      "title": "L25333-001 HP original touch IPS Display FHD glossy 60Hz",
      "url": "https://www.ipc-computer.eu/laptop-spare-parts/displays/display-l25333-001-75420185",
      "availability": "Out of stock EOL (End of Life) What does EOL mean?",
      "stock": "Out of stock",
      "isEol": true,
      "page": 671,
      "pageUrl": "https://www.ipc-computer.eu/laptop-spare-parts/displays?page=671"
    },
    {
      "title": "L47876-3D3 HP original touch IPS Display FHD glossy 60Hz",
      "url": "https://www.ipc-computer.eu/laptop-spare-parts/displays/display-l47876-3d3-101311233",
      "availability": "Out of stock EOL (End of Life) What does EOL mean?",
      "stock": "Out of stock",
      "isEol": true,
      "page": 671,
      "pageUrl": "https://www.ipc-computer.eu/laptop-spare-parts/displays?page=671"
    },
    {
      "title": "NV156FHM-T01 V8.0 BOE touch IPS Display FHD glossy 60Hz",
      "url": "https://www.ipc-computer.eu/laptop-spare-parts/displays/display-nv156fhm-t01-v8.0-75420195",
      "availability": "Out of stock EOL (End of Life) What does EOL mean?",
      "stock": "Out of stock",
      "isEol": true,
      "page": 671,
      "pageUrl": "https://www.ipc-computer.eu/laptop-spare-parts/displays?page=671"
    },
    {
      "title": "18010-15617900 Asus original TN Display FHD matt 60Hz",
      "url": "https://www.ipc-computer.eu/laptop-spare-parts/displays/display-18010-15617900-79265006",
      "availability": "Out of stock EOL (End of Life) What does EOL mean?",
      "stock": "Out of stock",
      "isEol": true,
      "page": 672,
      "pageUrl": "https://www.ipc-computer.eu/laptop-spare-parts/displays?page=672"
    },
    {
      "title": "18010-15619000 Asus original TN Display FHD matt 60Hz",
      "url": "https://www.ipc-computer.eu/laptop-spare-parts/displays/display-18010-15619000-102004117",
      "availability": "Out of stock EOL (End of Life) What does EOL mean?",
      "stock": "Out of stock",
      "isEol": true,
      "page": 672,
      "pageUrl": "https://www.ipc-computer.eu/laptop-spare-parts/displays?page=672"
    },
    {
      "title": "18010-15654500 Asus original TN Display HD matt 60Hz",
      "url": "https://www.ipc-computer.eu/laptop-spare-parts/displays/display-18010-15654500-144661731",
      "availability": "Out of stock EOL (End of Life) What does EOL mean?",
      "stock": "Out of stock",
      "isEol": true,
      "page": 672,
      "pageUrl": "https://www.ipc-computer.eu/laptop-spare-parts/displays?page=672"
    },
    {
      "title": "18010-15655200 Asus original TN Display FHD matt 60Hz",
      "url": "https://www.ipc-computer.eu/laptop-spare-parts/displays/display-18010-15655200-100140616",
      "availability": "Out of stock EOL (End of Life) What does EOL mean?",
      "stock": "Out of stock",
      "isEol": true,
      "page": 672,
      "pageUrl": "https://www.ipc-computer.eu/laptop-spare-parts/displays?page=672"
    },
    {
      "title": "18010-15656100 Asus original TN Display FHD matt 60Hz",
      "url": "https://www.ipc-computer.eu/laptop-spare-parts/displays/display-18010-15656100-79265008",
      "availability": "Out of stock EOL (End of Life) What does EOL mean?",
      "stock": "Out of stock",
      "isEol": true,
      "page": 672,
      "pageUrl": "https://www.ipc-computer.eu/laptop-spare-parts/displays?page=672"
    },
    {
      "title": "18010-15658300 Asus original TN Display FHD matt 60Hz",
      "url": "https://www.ipc-computer.eu/laptop-spare-parts/displays/display-18010-15658300-102004120",
      "availability": "Out of stock EOL (End of Life) What does EOL mean?",
      "stock": "Out of stock",
      "isEol": true,
      "page": 672,
      "pageUrl": "https://www.ipc-computer.eu/laptop-spare-parts/displays?page=672"
    },
    {
      "title": "18010-156B0400 Asus original TN Display FHD matt 60Hz",
      "url": "https://www.ipc-computer.eu/laptop-spare-parts/displays/display-18010-156b0400-102004122",
      "availability": "Out of stock EOL (End of Life) What does EOL mean?",
      "stock": "Out of stock",
      "isEol": true,
      "page": 672,
      "pageUrl": "https://www.ipc-computer.eu/laptop-spare-parts/displays?page=672"
    },
    {
      "title": "N156HGA-EA3 Innolux TN Display FHD matt 60Hz",
      "url": "https://www.ipc-computer.eu/laptop-spare-parts/displays/display-n156hga-ea3-79265057",
      "availability": "Out of stock EOL (End of Life) What does EOL mean?",
      "stock": "Out of stock",
      "isEol": true,
      "page": 672,
      "pageUrl": "https://www.ipc-computer.eu/laptop-spare-parts/displays?page=672"
    },
    {
      "title": "S1J-4E0A017-B51 MSI original IPS Display FHD matt 60Hz",
      "url": "https://www.ipc-computer.eu/laptop-spare-parts/displays/display-s1j-4e0a017-b51-84906513",
      "availability": "Out of stock EOL (End of Life) What does EOL mean?",
      "stock": "Out of stock",
      "isEol": true,
      "page": 672,
      "pageUrl": "https://www.ipc-computer.eu/laptop-spare-parts/displays?page=672"
    },
    {
      "title": "S1J-6E0A013-S02 MSI original IPS Display FHD matt 60Hz",
      "url": "https://www.ipc-computer.eu/laptop-spare-parts/displays/display-s1j-6e0a013-s02-85086056",
      "availability": "Out of stock EOL (End of Life) What does EOL mean?",
      "stock": "Out of stock",
      "isEol": true,
      "page": 672,
      "pageUrl": "https://www.ipc-computer.eu/laptop-spare-parts/displays?page=672"
    },
    {
      "title": "18010-13301800 Asus original IPS Display FHD matt 60Hz",
      "url": "https://www.ipc-computer.eu/laptop-spare-parts/displays/display-18010-13301800-101902766",
      "availability": "Out of stock EOL (End of Life) What does EOL mean?",
      "stock": "Out of stock",
      "isEol": true,
      "page": 673,
      "pageUrl": "https://www.ipc-computer.eu/laptop-spare-parts/displays?page=673"
    },
    {
      "title": "18200-15601700 Asus OLED Display FHD glossy 60Hz",
      "url": "https://www.ipc-computer.eu/laptop-spare-parts/displays/display-18200-15601700-144661809",
      "availability": "Out of stock EOL (End of Life) What does EOL mean?",
      "stock": "Out of stock",
      "isEol": true,
      "page": 673,
      "pageUrl": "https://www.ipc-computer.eu/laptop-spare-parts/displays?page=673"
    },
    {
      "title": "40070313 Medion original IPS Display FHD matt 144Hz (40Pin)",
      "url": "https://www.ipc-computer.eu/laptop-spare-parts/displays/display-40070313-101321571",
      "availability": "Out of stock EOL (End of Life) What does EOL mean?",
      "stock": "Out of stock",
      "isEol": true,
      "page": 673,
      "pageUrl": "https://www.ipc-computer.eu/laptop-spare-parts/displays?page=673"
    },
    {
      "title": "40073769 Medion original IPS Display FHD matt 144Hz (40Pin)",
      "url": "https://www.ipc-computer.eu/laptop-spare-parts/displays/display-40073769-99025786",
      "availability": "Out of stock EOL (End of Life) What does EOL mean?",
      "stock": "Out of stock",
      "isEol": true,
      "page": 673,
      "pageUrl": "https://www.ipc-computer.eu/laptop-spare-parts/displays?page=673"
    },
    {
      "title": "40077721 Medion original IPS Display FHD matt 144Hz (40Pin)",
      "url": "https://www.ipc-computer.eu/laptop-spare-parts/displays/display-40077721-98183315",
      "availability": "Out of stock EOL (End of Life) What does EOL mean?",
      "stock": "Out of stock",
      "isEol": true,
      "page": 673,
      "pageUrl": "https://www.ipc-computer.eu/laptop-spare-parts/displays?page=673"
    },
    {
      "title": "40080055 Medion original IPS Display FHD matt 60Hz",
      "url": "https://www.ipc-computer.eu/laptop-spare-parts/displays/display-40080055-98742618",
      "availability": "Out of stock EOL (End of Life) What does EOL mean?",
      "stock": "Out of stock",
      "isEol": true,
      "page": 673,
      "pageUrl": "https://www.ipc-computer.eu/laptop-spare-parts/displays?page=673"
    },
    {
      "title": "5D11D04807 Lenovo original IPS Display WQHD matt 165Hz",
      "url": "https://www.ipc-computer.eu/laptop-spare-parts/displays/display-5d11d04807-102157420",
      "availability": "Out of stock EOL (End of Life) What does EOL mean?",
      "stock": "Out of stock",
      "isEol": true,
      "page": 673,
      "pageUrl": "https://www.ipc-computer.eu/laptop-spare-parts/displays?page=673"
    },
    {
      "title": "KL.1400C.001 Acer original IPS Display FHD matt 144Hz",
      "url": "https://www.ipc-computer.eu/laptop-spare-parts/displays/display-kl.1400c.001-99025948",
      "availability": "Out of stock EOL (End of Life) What does EOL mean?",
      "stock": "Out of stock",
      "isEol": true,
      "page": 673,
      "pageUrl": "https://www.ipc-computer.eu/laptop-spare-parts/displays?page=673"
    },
    {
      "title": "S1J-6E0A028-A90 MSI original IPS Display FHD matt 60Hz",
      "url": "https://www.ipc-computer.eu/laptop-spare-parts/displays/display-s1j-6e0a028-a90-85086064",
      "availability": "Out of stock EOL (End of Life) What does EOL mean?",
      "stock": "Out of stock",
      "isEol": true,
      "page": 673,
      "pageUrl": "https://www.ipc-computer.eu/laptop-spare-parts/displays?page=673"
    },
    {
      "title": "S1J-6E0A049-I75 MSI original IPS Display FHD matt 60Hz",
      "url": "https://www.ipc-computer.eu/laptop-spare-parts/displays/display-s1j-6e0a049-i75-89406555",
      "availability": "Out of stock EOL (End of Life) What does EOL mean?",
      "stock": "Out of stock",
      "isEol": true,
      "page": 673,
      "pageUrl": "https://www.ipc-computer.eu/laptop-spare-parts/displays?page=673"
    },
    {
      "title": "0C17681 Lenovo TN Display FHD matt 60Hz",
      "url": "https://www.ipc-computer.eu/laptop-spare-parts/displays/display-0c17681-101298230",
      "availability": "Out of stock EOL (End of Life) What does EOL mean?",
      "stock": "Out of stock",
      "isEol": true,
      "page": 674,
      "pageUrl": "https://www.ipc-computer.eu/laptop-spare-parts/displays?page=674"
    },
    {
      "title": "18010-14070600 Asus original TN Display WQXGA matt 60Hz",
      "url": "https://www.ipc-computer.eu/laptop-spare-parts/displays/display-18010-14070600-103277673",
      "availability": "Out of stock EOL (End of Life) What does EOL mean?",
      "stock": "Out of stock",
      "isEol": true,
      "page": 674,
      "pageUrl": "https://www.ipc-computer.eu/laptop-spare-parts/displays?page=674"
    },
    {
      "title": "18010-15605700 Asus original IPS Display FHD matt 60Hz",
      "url": "https://www.ipc-computer.eu/laptop-spare-parts/displays/display-18010-15605700-144661713",
      "availability": "Out of stock EOL (End of Life) What does EOL mean?",
      "stock": "Out of stock",
      "isEol": true,
      "page": 674,
      "pageUrl": "https://www.ipc-computer.eu/laptop-spare-parts/displays?page=674"
    },
    {
      "title": "18010-17323700 Asus original IPS Display FHD matt 144Hz",
      "url": "https://www.ipc-computer.eu/laptop-spare-parts/displays/display-18010-17323700-103100059",
      "availability": "Out of stock EOL (End of Life) What does EOL mean?",
      "stock": "Out of stock",
      "isEol": true,
      "page": 674,
      "pageUrl": "https://www.ipc-computer.eu/laptop-spare-parts/displays?page=674"
    },
    {
      "title": "18010-17350900 Asus original IPS Display FHD matt 144Hz",
      "url": "https://www.ipc-computer.eu/laptop-spare-parts/displays/display-18010-17350900-103100062",
      "availability": "Out of stock EOL (End of Life) What does EOL mean?",
      "stock": "Out of stock",
      "isEol": true,
      "page": 674,
      "pageUrl": "https://www.ipc-computer.eu/laptop-spare-parts/displays?page=674"
    },
    {
      "title": "18010-17360000 Asus original IPS Display FHD matt 144Hz",
      "url": "https://www.ipc-computer.eu/laptop-spare-parts/displays/display-18010-17360000-103100063",
      "availability": "Out of stock EOL (End of Life) What does EOL mean?",
      "stock": "Out of stock",
      "isEol": true,
      "page": 674,
      "pageUrl": "https://www.ipc-computer.eu/laptop-spare-parts/displays?page=674"
    },
    {
      "title": "5D11D04809 Lenovo original IPS Display WQHD matt 165Hz",
      "url": "https://www.ipc-computer.eu/laptop-spare-parts/displays/display-5d11d04809-102157421",
      "availability": "Out of stock EOL (End of Life) What does EOL mean?",
      "stock": "Out of stock",
      "isEol": true,
      "page": 674,
      "pageUrl": "https://www.ipc-computer.eu/laptop-spare-parts/displays?page=674"
    },
    {
      "title": "5D11D04810 Lenovo original IPS Display WQHD matt 165Hz",
      "url": "https://www.ipc-computer.eu/laptop-spare-parts/displays/display-5d11d04810-102157422",
      "availability": "Out of stock EOL (End of Life) What does EOL mean?",
      "stock": "Out of stock",
      "isEol": true,
      "page": 674,
      "pageUrl": "https://www.ipc-computer.eu/laptop-spare-parts/displays?page=674"
    },
    {
      "title": "9FN4Y Dell TN Display FHD matt 60Hz",
      "url": "https://www.ipc-computer.eu/laptop-spare-parts/displays/display-9fn4y-101298249",
      "availability": "Out of stock EOL (End of Life) What does EOL mean?",
      "stock": "Out of stock",
      "isEol": true,
      "page": 674,
      "pageUrl": "https://www.ipc-computer.eu/laptop-spare-parts/displays?page=674"
    },
    {
      "title": "Asus 18010-15680900 Display",
      "url": "https://www.ipc-computer.eu/laptop-spare-parts/displays/display-18010-15680900-122712499",
      "availability": "Out of stock EOL (End of Life) What does EOL mean?",
      "stock": "Out of stock",
      "isEol": true,
      "page": 674,
      "pageUrl": "https://www.ipc-computer.eu/laptop-spare-parts/displays?page=674"
    },
    {
      "title": "18010-14053100 Asus original TN Display HD matt 60Hz",
      "url": "https://www.ipc-computer.eu/laptop-spare-parts/displays/display-18010-14053100-74295352",
      "availability": "Out of stock EOL (End of Life) What does EOL mean?",
      "stock": "Out of stock",
      "isEol": true,
      "page": 675,
      "pageUrl": "https://www.ipc-computer.eu/laptop-spare-parts/displays?page=675"
    },
    {
      "title": "18010-15606400 Asus original TN Display FHD matt 60Hz",
      "url": "https://www.ipc-computer.eu/laptop-spare-parts/displays/display-18010-15606400-79265003",
      "availability": "Out of stock EOL (End of Life) What does EOL mean?",
      "stock": "Out of stock",
      "isEol": true,
      "page": 675,
      "pageUrl": "https://www.ipc-computer.eu/laptop-spare-parts/displays?page=675"
    },
    {
      "title": "18010-17350400 Asus original TN Display HD+ matt 60Hz",
      "url": "https://www.ipc-computer.eu/laptop-spare-parts/displays/display-18010-17350400-73682558/nup",
      "availability": "Out of stock EOL (End of Life) What does EOL mean?",
      "stock": "Out of stock",
      "isEol": true,
      "page": 675,
      "pageUrl": "https://www.ipc-computer.eu/laptop-spare-parts/displays?page=675"
    },
    {
      "title": "KL.1560D.020 Acer original TN Display HD glossy 60Hz",
      "url": "https://www.ipc-computer.eu/laptop-spare-parts/displays/display-kl.1560d.020-52056080/nup",
      "availability": "Out of stock EOL (End of Life) What does EOL mean?",
      "stock": "Out of stock",
      "isEol": true,
      "page": 675,
      "pageUrl": "https://www.ipc-computer.eu/laptop-spare-parts/displays?page=675"
    },
    {
      "title": "L44037-L92 HP original IPS Display FHD matt 60Hz",
      "url": "https://www.ipc-computer.eu/laptop-spare-parts/displays/display-l44037-l92-76073978",
      "availability": "Out of stock EOL (End of Life) What does EOL mean?",
      "stock": "Out of stock",
      "isEol": true,
      "page": 675,
      "pageUrl": "https://www.ipc-computer.eu/laptop-spare-parts/displays?page=675"
    },
    {
      "title": "M16342-001 HP original touch IPS Display FHD glossy 60Hz",
      "url": "https://www.ipc-computer.eu/laptop-spare-parts/displays/display-m16342-001-100624882",
      "availability": "Out of stock EOL (End of Life) What does EOL mean?",
      "stock": "Out of stock",
      "isEol": true,
      "page": 675,
      "pageUrl": "https://www.ipc-computer.eu/laptop-spare-parts/displays?page=675"
    },
    {
      "title": "N140BGA-EA4 Innolux TN Display HD matt 60Hz",
      "url": "https://www.ipc-computer.eu/laptop-spare-parts/displays/display-n140bga-ea4-121139323",
      "availability": "Out of stock EOL (End of Life) What does EOL mean?",
      "stock": "Out of stock",
      "isEol": true,
      "page": 675,
      "pageUrl": "https://www.ipc-computer.eu/laptop-spare-parts/displays?page=675"
    },
    {
      "title": "N173FGA-E34 Rev. C2 Innolux TN Display HD+ matt 60Hz",
      "url": "https://www.ipc-computer.eu/laptop-spare-parts/displays/display-n173fga-e34-rev.-c2-76023139",
      "availability": "Out of stock EOL (End of Life) What does EOL mean?",
      "stock": "Out of stock",
      "isEol": true,
      "page": 675,
      "pageUrl": "https://www.ipc-computer.eu/laptop-spare-parts/displays?page=675"
    },
    {
      "title": "N173HCE-G33 C3 Innolux IPS Display FHD matt 144Hz",
      "url": "https://www.ipc-computer.eu/laptop-spare-parts/displays/display-n173hce-g33-c3-101301219",
      "availability": "Out of stock EOL (End of Life) What does EOL mean?",
      "stock": "Out of stock",
      "isEol": true,
      "page": 675,
      "pageUrl": "https://www.ipc-computer.eu/laptop-spare-parts/displays?page=675"
    },
    {
      "title": "S1J-JE0A010-A90 MSI original IPS Display FHD matt 144Hz",
      "url": "https://www.ipc-computer.eu/laptop-spare-parts/displays/display-s1j-je0a010-a90-85086070",
      "availability": "Out of stock EOL (End of Life) What does EOL mean?",
      "stock": "Out of stock",
      "isEol": true,
      "page": 675,
      "pageUrl": "https://www.ipc-computer.eu/laptop-spare-parts/displays?page=675"
    },
    {
      "title": "18010-14002500 Asus original IPS Display FHD matt 60Hz",
      "url": "https://www.ipc-computer.eu/laptop-spare-parts/displays/display-18010-14002500-101303359",
      "availability": "Out of stock EOL (End of Life) What does EOL mean?",
      "stock": "Out of stock",
      "isEol": true,
      "page": 676,
      "pageUrl": "https://www.ipc-computer.eu/laptop-spare-parts/displays?page=676"
    },
    {
      "title": "18010-15615600 Asus original TN Display FHD glossy 60Hz",
      "url": "https://www.ipc-computer.eu/laptop-spare-parts/displays/display-18010-15615600-62345067",
      "availability": "Out of stock EOL (End of Life) What does EOL mean?",
      "stock": "Out of stock",
      "isEol": true,
      "page": 676,
      "pageUrl": "https://www.ipc-computer.eu/laptop-spare-parts/displays?page=676"
    },
    {
      "title": "18010-17321500 Asus original IPS Display FHD matt 60Hz",
      "url": "https://www.ipc-computer.eu/laptop-spare-parts/displays/display-18010-17321500-88478251",
      "availability": "Out of stock EOL (End of Life) What does EOL mean?",
      "stock": "Out of stock",
      "isEol": true,
      "page": 676,
      "pageUrl": "https://www.ipc-computer.eu/laptop-spare-parts/displays?page=676"
    },
    {
      "title": "18010-17324400 Asus original IPS Display FHD matt 144Hz",
      "url": "https://www.ipc-computer.eu/laptop-spare-parts/displays/display-18010-17324400-103100060",
      "availability": "Out of stock EOL (End of Life) What does EOL mean?",
      "stock": "Out of stock",
      "isEol": true,
      "page": 676,
      "pageUrl": "https://www.ipc-computer.eu/laptop-spare-parts/displays?page=676"
    },
    {
      "title": "18010-17330800 Asus original IPS Display FHD matt 60Hz",
      "url": "https://www.ipc-computer.eu/laptop-spare-parts/displays/display-18010-17330800-88643728",
      "availability": "Out of stock EOL (End of Life) What does EOL mean?",
      "stock": "Out of stock",
      "isEol": true,
      "page": 676,
      "pageUrl": "https://www.ipc-computer.eu/laptop-spare-parts/displays?page=676"
    },
    {
      "title": "90AI0052-R20021 Asus original touch AMOLED Display HDR (HDR10+) glossy 144Hz",
      "url": "https://www.ipc-computer.eu/laptop-spare-parts/displays/display-90ai0052-r20021-101529796",
      "availability": "Out of stock EOL (End of Life) What does EOL mean?",
      "stock": "Out of stock",
      "isEol": true,
      "page": 676,
      "pageUrl": "https://www.ipc-computer.eu/laptop-spare-parts/displays?page=676"
    },
    {
      "title": "B133HAN05.C 2A AU Optronics IPS Display FHD matt 60Hz",
      "url": "https://www.ipc-computer.eu/laptop-spare-parts/displays/display-b133han05.c-2a-88538288",
      "availability": "Out of stock EOL (End of Life) What does EOL mean?",
      "stock": "Out of stock",
      "isEol": true,
      "page": 676,
      "pageUrl": "https://www.ipc-computer.eu/laptop-spare-parts/displays?page=676"
    },
    {
      "title": "KL.1730D.002 Acer TN Display FHD matt 60Hz",
      "url": "https://www.ipc-computer.eu/laptop-spare-parts/displays/display-kl.1730d.002-73320361/nup",
      "availability": "Out of stock EOL (End of Life) What does EOL mean?",
      "stock": "Out of stock",
      "isEol": true,
      "page": 676,
      "pageUrl": "https://www.ipc-computer.eu/laptop-spare-parts/displays?page=676"
    },
    {
      "title": "LQ173D1JW31 Sharp IPS Display UHD matt 60Hz",
      "url": "https://www.ipc-computer.eu/laptop-spare-parts/displays/display-lq173d1jw31-62028870",
      "availability": "Out of stock EOL (End of Life) What does EOL mean?",
      "stock": "Out of stock",
      "isEol": true,
      "page": 676,
      "pageUrl": "https://www.ipc-computer.eu/laptop-spare-parts/displays?page=676"
    },
    {
      "title": "NT156FHM-N62 BOE TN Display FHD matt 60Hz",
      "url": "https://www.ipc-computer.eu/laptop-spare-parts/displays/display-nt156fhm-n62-79265058",
      "availability": "Out of stock EOL (End of Life) What does EOL mean?",
      "stock": "Out of stock",
      "isEol": true,
      "page": 676,
      "pageUrl": "https://www.ipc-computer.eu/laptop-spare-parts/displays?page=676"
    },
    {
      "title": "18010-13302300 Asus original IPS Display FHD matt 60Hz",
      "url": "https://www.ipc-computer.eu/laptop-spare-parts/displays/display-18010-13302300-88538219",
      "availability": "Out of stock EOL (End of Life) What does EOL mean?",
      "stock": "Out of stock",
      "isEol": true,
      "page": 677,
      "pageUrl": "https://www.ipc-computer.eu/laptop-spare-parts/displays?page=677"
    },
    {
      "title": "18010-14003300 Asus original TN Display HD matt 60Hz",
      "url": "https://www.ipc-computer.eu/laptop-spare-parts/displays/display-18010-14003300-76031765",
      "availability": "Out of stock EOL (End of Life) What does EOL mean?",
      "stock": "Out of stock",
      "isEol": true,
      "page": 677,
      "pageUrl": "https://www.ipc-computer.eu/laptop-spare-parts/displays?page=677"
    },
    {
      "title": "42T0742 Lenovo TN Display HD+ matt 60Hz",
      "url": "https://www.ipc-computer.eu/laptop-spare-parts/displays/display-42t0742-72404482/nup",
      "availability": "Out of stock EOL (End of Life) What does EOL mean?",
      "stock": "Out of stock",
      "isEol": true,
      "page": 677,
      "pageUrl": "https://www.ipc-computer.eu/laptop-spare-parts/displays?page=677"
    },
    {
      "title": "KL.15605.029 Acer original TN Display HD glossy 60Hz",
      "url": "https://www.ipc-computer.eu/laptop-spare-parts/displays/display-kl.15605.029-53530508",
      "availability": "Out of stock EOL (End of Life) What does EOL mean?",
      "stock": "Out of stock",
      "isEol": true,
      "page": 677,
      "pageUrl": "https://www.ipc-computer.eu/laptop-spare-parts/displays?page=677"
    },
    {
      "title": "KL.1560D.012 Acer original TN Display HD matt 60Hz",
      "url": "https://www.ipc-computer.eu/laptop-spare-parts/displays/display-kl.1560d.012-50860876/nup",
      "availability": "Out of stock EOL (End of Life) What does EOL mean?",
      "stock": "Out of stock",
      "isEol": true,
      "page": 677,
      "pageUrl": "https://www.ipc-computer.eu/laptop-spare-parts/displays?page=677"
    },
    {
      "title": "KL.17308.002 Acer original Display HD+ glossy",
      "url": "https://www.ipc-computer.eu/laptop-spare-parts/displays/display-kl.17308.002-52056082",
      "availability": "Out of stock EOL (End of Life) What does EOL mean?",
      "stock": "Out of stock",
      "isEol": true,
      "page": 677,
      "pageUrl": "https://www.ipc-computer.eu/laptop-spare-parts/displays?page=677"
    },
    {
      "title": "KL.2380E.011 Acer original IPS Display FHD matt 75Hz",
      "url": "https://www.ipc-computer.eu/laptop-spare-parts/displays/display-kl.2380e.011-99868664",
      "availability": "Out of stock EOL (End of Life) What does EOL mean?",
      "stock": "Out of stock",
      "isEol": true,
      "page": 677,
      "pageUrl": "https://www.ipc-computer.eu/laptop-spare-parts/displays?page=677"
    },
    {
      "title": "L19198-001 HP original IPS Display FHD matt 60Hz",
      "url": "https://www.ipc-computer.eu/laptop-spare-parts/displays/display-l19198-001-76073973",
      "availability": "Out of stock EOL (End of Life) What does EOL mean?",
      "stock": "Out of stock",
      "isEol": true,
      "page": 677,
      "pageUrl": "https://www.ipc-computer.eu/laptop-spare-parts/displays?page=677"
    },
    {
      "title": "N173HGE-E11 Innolux TN Display FHD glossy 60Hz",
      "url": "https://www.ipc-computer.eu/laptop-spare-parts/displays/display-n173hge-e11-69607819/nup",
      "availability": "Out of stock EOL (End of Life) What does EOL mean?",
      "stock": "Out of stock",
      "isEol": true,
      "page": 677,
      "pageUrl": "https://www.ipc-computer.eu/laptop-spare-parts/displays?page=677"
    },
    {
      "title": "SD10M68024 Lenovo IPS Display UHD matt 60Hz",
      "url": "https://www.ipc-computer.eu/laptop-spare-parts/displays/display-sd10m68024-69808056",
      "availability": "Out of stock EOL (End of Life) What does EOL mean?",
      "stock": "Out of stock",
      "isEol": true,
      "page": 677,
      "pageUrl": "https://www.ipc-computer.eu/laptop-spare-parts/displays?page=677"
    },
    {
      "title": "18010-15614500 Asus original IPS Display FHD matt 60Hz",
      "url": "https://www.ipc-computer.eu/laptop-spare-parts/displays/display-18010-15614500-144661716",
      "availability": "Out of stock EOL (End of Life) What does EOL mean?",
      "stock": "Out of stock",
      "isEol": true,
      "page": 678,
      "pageUrl": "https://www.ipc-computer.eu/laptop-spare-parts/displays?page=678"
    },
    {
      "title": "18010-17350700 Asus original IPS Display FHD matt 144Hz",
      "url": "https://www.ipc-computer.eu/laptop-spare-parts/displays/display-18010-17350700-103100061",
      "availability": "Out of stock EOL (End of Life) What does EOL mean?",
      "stock": "Out of stock",
      "isEol": true,
      "page": 678,
      "pageUrl": "https://www.ipc-computer.eu/laptop-spare-parts/displays?page=678"
    },
    {
      "title": "Asus 18010-15680800 Display",
      "url": "https://www.ipc-computer.eu/laptop-spare-parts/displays/display-18010-15680800-122712498",
      "availability": "Out of stock EOL (End of Life) What does EOL mean?",
      "stock": "Out of stock",
      "isEol": true,
      "page": 678,
      "pageUrl": "https://www.ipc-computer.eu/laptop-spare-parts/displays?page=678"
    },
    {
      "title": "B156HTN03.3 AU Optronics TN Display FHD matt 60Hz",
      "url": "https://www.ipc-computer.eu/laptop-spare-parts/displays/display-b156htn03.3-101298253",
      "availability": "Out of stock EOL (End of Life) What does EOL mean?",
      "stock": "Out of stock",
      "isEol": true,
      "page": 678,
      "pageUrl": "https://www.ipc-computer.eu/laptop-spare-parts/displays?page=678"
    },
    {
      "title": "CP454836-XX Fujitsu TN Display HD+ matt 60Hz",
      "url": "https://www.ipc-computer.eu/laptop-spare-parts/displays/display-cp454836-xx-72404555/nup",
      "availability": "Out of stock EOL (End of Life) What does EOL mean?",
      "stock": "Out of stock",
      "isEol": true,
      "page": 678,
      "pageUrl": "https://www.ipc-computer.eu/laptop-spare-parts/displays?page=678"
    },
    {
      "title": "CP517709-XX Fujitsu TN Display FHD matt 60Hz",
      "url": "https://www.ipc-computer.eu/laptop-spare-parts/displays/display-cp517709-xx-73320315/nup",
      "availability": "Out of stock EOL (End of Life) What does EOL mean?",
      "stock": "Out of stock",
      "isEol": true,
      "page": 678,
      "pageUrl": "https://www.ipc-computer.eu/laptop-spare-parts/displays?page=678"
    },
    {
      "title": "L01674-001 HP original IPS Display FHD glossy 60Hz",
      "url": "https://www.ipc-computer.eu/laptop-spare-parts/displays/display-l01674-001-53612808",
      "availability": "Out of stock EOL (End of Life) What does EOL mean?",
      "stock": "Out of stock",
      "isEol": true,
      "page": 678,
      "pageUrl": "https://www.ipc-computer.eu/laptop-spare-parts/displays?page=678"
    },
    {
      "title": "N00084-001 HP original IPS Display FHD matt 60Hz",
      "url": "https://www.ipc-computer.eu/laptop-spare-parts/displays/display-n00084-001-91681287",
      "availability": "Out of stock EOL (End of Life) What does EOL mean?",
      "stock": "Out of stock",
      "isEol": true,
      "page": 678,
      "pageUrl": "https://www.ipc-computer.eu/laptop-spare-parts/displays?page=678"
    },
    {
      "title": "S1J-7E0A023-I75 MSI IPS Display matt 120Hz (120Hz / 40-Pin eDP)",
      "url": "https://www.ipc-computer.eu/laptop-spare-parts/displays/display-s1j-7e0a023-i75-97361940",
      "availability": "Out of stock EOL (End of Life) What does EOL mean?",
      "stock": "Out of stock",
      "isEol": true,
      "page": 678,
      "pageUrl": "https://www.ipc-computer.eu/laptop-spare-parts/displays?page=678"
    },
    {
      "title": "V000100790 Toshiba TN Display WXGA matt 60Hz",
      "url": "https://www.ipc-computer.eu/laptop-spare-parts/displays/display-v000100790-18939277/nup",
      "availability": "Out of stock EOL (End of Life) What does EOL mean?",
      "stock": "Out of stock",
      "isEol": true,
      "page": 678,
      "pageUrl": "https://www.ipc-computer.eu/laptop-spare-parts/displays?page=678"
    },
    {
      "title": "0DD282 Dell TN Display WXGA matt 60Hz",
      "url": "https://www.ipc-computer.eu/laptop-spare-parts/displays/display-0dd282-18896276/nup",
      "availability": "Out of stock EOL (End of Life) What does EOL mean?",
      "stock": "Out of stock",
      "isEol": true,
      "page": 679,
      "pageUrl": "https://www.ipc-computer.eu/laptop-spare-parts/displays?page=679"
    },
    {
      "title": "0T892T Dell TN Display HD matt 60Hz",
      "url": "https://www.ipc-computer.eu/laptop-spare-parts/displays/display-0t892t-47344896",
      "availability": "Out of stock EOL (End of Life) What does EOL mean?",
      "stock": "Out of stock",
      "isEol": true,
      "page": 679,
      "pageUrl": "https://www.ipc-computer.eu/laptop-spare-parts/displays?page=679"
    },
    {
      "title": "18G241840130Q Asus TN Display FHD glossy 60Hz",
      "url": "https://www.ipc-computer.eu/laptop-spare-parts/displays/display-18g241840130q-32726746/nup",
      "availability": "Out of stock EOL (End of Life) What does EOL mean?",
      "stock": "Out of stock",
      "isEol": true,
      "page": 679,
      "pageUrl": "https://www.ipc-computer.eu/laptop-spare-parts/displays?page=679"
    },
    {
      "title": "HSD173PUW1 HannStar TN Display FHD matt 60Hz",
      "url": "https://www.ipc-computer.eu/laptop-spare-parts/displays/display-hsd173puw1-73320347/nup",
      "availability": "Out of stock EOL (End of Life) What does EOL mean?",
      "stock": "Out of stock",
      "isEol": true,
      "page": 679,
      "pageUrl": "https://www.ipc-computer.eu/laptop-spare-parts/displays?page=679"
    },
    {
      "title": "KL.15608.018 Acer original Display HD glossy",
      "url": "https://www.ipc-computer.eu/laptop-spare-parts/displays/display-kl.15608.018-52937401/nup",
      "availability": "Out of stock EOL (End of Life) What does EOL mean?",
      "stock": "Out of stock",
      "isEol": true,
      "page": 679,
      "pageUrl": "https://www.ipc-computer.eu/laptop-spare-parts/displays?page=679"
    },
    {
      "title": "L78065-001 HP original IPS Display FHD matt 60Hz",
      "url": "https://www.ipc-computer.eu/laptop-spare-parts/displays/display-l78065-001-78931740",
      "availability": "Out of stock EOL (End of Life) What does EOL mean?",
      "stock": "Out of stock",
      "isEol": true,
      "page": 679,
      "pageUrl": "https://www.ipc-computer.eu/laptop-spare-parts/displays?page=679"
    },
    {
      "title": "LTN140KT04 Samsung TN Display HD+ matt 60Hz",
      "url": "https://www.ipc-computer.eu/laptop-spare-parts/displays/display-ltn140kt04-32733547/nup",
      "availability": "Out of stock EOL (End of Life) What does EOL mean?",
      "stock": "Out of stock",
      "isEol": true,
      "page": 679,
      "pageUrl": "https://www.ipc-computer.eu/laptop-spare-parts/displays?page=679"
    },
    {
      "title": "N154I1-L09 Chi Mei TN Display WXGA matt 60Hz",
      "url": "https://www.ipc-computer.eu/laptop-spare-parts/displays/display-n154i1-l09-27499661/nup",
      "availability": "Out of stock EOL (End of Life) What does EOL mean?",
      "stock": "Out of stock",
      "isEol": true,
      "page": 679,
      "pageUrl": "https://www.ipc-computer.eu/laptop-spare-parts/displays?page=679"
    },
    {
      "title": "N184H4-L04 Chi Mei TN Display FHD glossy 60Hz",
      "url": "https://www.ipc-computer.eu/laptop-spare-parts/displays/display-n184h4-l04-32733884/nup",
      "availability": "Out of stock EOL (End of Life) What does EOL mean?",
      "stock": "Out of stock",
      "isEol": true,
      "page": 679,
      "pageUrl": "https://www.ipc-computer.eu/laptop-spare-parts/displays?page=679"
    },
    {
      "title": "V000080320 Toshiba TN Display WXGA matt 60Hz",
      "url": "https://www.ipc-computer.eu/laptop-spare-parts/displays/display-v000080320-18939249/nup",
      "availability": "Out of stock EOL (End of Life) What does EOL mean?",
      "stock": "Out of stock",
      "isEol": true,
      "page": 679,
      "pageUrl": "https://www.ipc-computer.eu/laptop-spare-parts/displays?page=679"
    },
    {
      "title": "B154EW09 AU Optronics TN Display WXGA glossy 60Hz",
      "url": "https://www.ipc-computer.eu/laptop-spare-parts/displays/display-b154ew09-32730481",
      "availability": "Out of stock EOL (End of Life) What does EOL mean?",
      "stock": "Out of stock",
      "isEol": true,
      "page": 680,
      "pageUrl": "https://www.ipc-computer.eu/laptop-spare-parts/displays?page=680"
    },
    {
      "title": "B156HAN02.2 H/W:1A F/W:1 AU Optronics IPS Display FHD glossy 60Hz",
      "url": "https://www.ipc-computer.eu/laptop-spare-parts/displays/display-b156han02.2-h-w-1a-f-w-1-58259095",
      "availability": "Out of stock EOL (End of Life) What does EOL mean?",
      "stock": "Out of stock",
      "isEol": true,
      "page": 680,
      "pageUrl": "https://www.ipc-computer.eu/laptop-spare-parts/displays?page=680"
    },
    {
      "title": "BA59-03388A Samsung TN Display FHD matt 60Hz",
      "url": "https://www.ipc-computer.eu/laptop-spare-parts/displays/display-ba59-03388a-73320305/nup",
      "availability": "Out of stock EOL (End of Life) What does EOL mean?",
      "stock": "Out of stock",
      "isEol": true,
      "page": 680,
      "pageUrl": "https://www.ipc-computer.eu/laptop-spare-parts/displays?page=680"
    },
    {
      "title": "L17303-J73 HP original IPS Display FHD glossy 60Hz",
      "url": "https://www.ipc-computer.eu/laptop-spare-parts/displays/display-l17303-j73-74962017",
      "availability": "Out of stock EOL (End of Life) What does EOL mean?",
      "stock": "Out of stock",
      "isEol": true,
      "page": 680,
      "pageUrl": "https://www.ipc-computer.eu/laptop-spare-parts/displays?page=680"
    },
    {
      "title": "LK.15404.004 Acer TN Display WXGA matt 60Hz",
      "url": "https://www.ipc-computer.eu/laptop-spare-parts/displays/display-lk.15404.004-18929414/nup",
      "availability": "Out of stock EOL (End of Life) What does EOL mean?",
      "stock": "Out of stock",
      "isEol": true,
      "page": 680,
      "pageUrl": "https://www.ipc-computer.eu/laptop-spare-parts/displays?page=680"
    },
    {
      "title": "LK.15409.005 Acer TN Display WXGA matt 60Hz",
      "url": "https://www.ipc-computer.eu/laptop-spare-parts/displays/display-lk.15409.005-18929509/nup",
      "availability": "Out of stock EOL (End of Life) What does EOL mean?",
      "stock": "Out of stock",
      "isEol": true,
      "page": 680,
      "pageUrl": "https://www.ipc-computer.eu/laptop-spare-parts/displays?page=680"
    },
    {
      "title": "LK.15605.027 Acer TN Display HD matt 60Hz",
      "url": "https://www.ipc-computer.eu/laptop-spare-parts/displays/display-lk.15605.027-47344938",
      "availability": "Out of stock EOL (End of Life) What does EOL mean?",
      "stock": "Out of stock",
      "isEol": true,
      "page": 680,
      "pageUrl": "https://www.ipc-computer.eu/laptop-spare-parts/displays?page=680"
    },
    {
      "title": "LK.1840D.003 Acer TN Display FHD glossy 60Hz",
      "url": "https://www.ipc-computer.eu/laptop-spare-parts/displays/display-lk.1840d.003-32733322/nup",
      "availability": "Out of stock EOL (End of Life) What does EOL mean?",
      "stock": "Out of stock",
      "isEol": true,
      "page": 680,
      "pageUrl": "https://www.ipc-computer.eu/laptop-spare-parts/displays?page=680"
    },
    {
      "title": "LP173WF1 LG TN Display FHD matt 60Hz",
      "url": "https://www.ipc-computer.eu/laptop-spare-parts/displays/display-lp173wf1-73320405/nup",
      "availability": "Out of stock EOL (End of Life) What does EOL mean?",
      "stock": "Out of stock",
      "isEol": true,
      "page": 680,
      "pageUrl": "https://www.ipc-computer.eu/laptop-spare-parts/displays?page=680"
    },
    {
      "title": "M22912-001 HP original IPS Display FHD matt 60Hz",
      "url": "https://www.ipc-computer.eu/laptop-spare-parts/displays/display-m22912-001-80236627",
      "availability": "Out of stock EOL (End of Life) What does EOL mean?",
      "stock": "Out of stock",
      "isEol": true,
      "page": 680,
      "pageUrl": "https://www.ipc-computer.eu/laptop-spare-parts/displays?page=680"
    },
    {
      "title": "18G241730310Q Asus TN Display FHD matt 60Hz",
      "url": "https://www.ipc-computer.eu/laptop-spare-parts/displays/display-18g241730310q-73320252/nup",
      "availability": "Out of stock EOL (End of Life) What does EOL mean?",
      "stock": "Out of stock",
      "isEol": true,
      "page": 681,
      "pageUrl": "https://www.ipc-computer.eu/laptop-spare-parts/displays?page=681"
    },
    {
      "title": "646977-001 HP TN Display HD+ matt 60Hz",
      "url": "https://www.ipc-computer.eu/laptop-spare-parts/displays/display-646977-001-72404507/nup",
      "availability": "Out of stock EOL (End of Life) What does EOL mean?",
      "stock": "Out of stock",
      "isEol": true,
      "page": 681,
      "pageUrl": "https://www.ipc-computer.eu/laptop-spare-parts/displays?page=681"
    },
    {
      "title": "B154EW01 AU Optronics TN Display WXGA matt 60Hz",
      "url": "https://www.ipc-computer.eu/laptop-spare-parts/displays/display-b154ew01-18916530/nup",
      "availability": "Out of stock EOL (End of Life) What does EOL mean?",
      "stock": "Out of stock",
      "isEol": true,
      "page": 681,
      "pageUrl": "https://www.ipc-computer.eu/laptop-spare-parts/displays?page=681"
    },
    {
      "title": "CLAA154WA01AQ Chungwa TN Display WXGA matt 60Hz",
      "url": "https://www.ipc-computer.eu/laptop-spare-parts/displays/display-claa154wa01aq-27499540/nup",
      "availability": "Out of stock EOL (End of Life) What does EOL mean?",
      "stock": "Out of stock",
      "isEol": true,
      "page": 681,
      "pageUrl": "https://www.ipc-computer.eu/laptop-spare-parts/displays?page=681"
    },
    {
      "title": "G370R Dell TN Display HD+ matt 60Hz",
      "url": "https://www.ipc-computer.eu/laptop-spare-parts/displays/display-g370r-72404571/nup",
      "availability": "Out of stock EOL (End of Life) What does EOL mean?",
      "stock": "Out of stock",
      "isEol": true,
      "page": 681,
      "pageUrl": "https://www.ipc-computer.eu/laptop-spare-parts/displays?page=681"
    },
    {
      "title": "HDKPV Dell TN Display FHD matt 60Hz",
      "url": "https://www.ipc-computer.eu/laptop-spare-parts/displays/display-hdkpv-73320345/nup",
      "availability": "Out of stock EOL (End of Life) What does EOL mean?",
      "stock": "Out of stock",
      "isEol": true,
      "page": 681,
      "pageUrl": "https://www.ipc-computer.eu/laptop-spare-parts/displays?page=681"
    },
    {
      "title": "LK.15406.025 Acer TN Display WXGA matt 60Hz",
      "url": "https://www.ipc-computer.eu/laptop-spare-parts/displays/display-lk.15406.025-25949007/nup",
      "availability": "Out of stock EOL (End of Life) What does EOL mean?",
      "stock": "Out of stock",
      "isEol": true,
      "page": 681,
      "pageUrl": "https://www.ipc-computer.eu/laptop-spare-parts/displays?page=681"
    },
    {
      "title": "MJ154 Dell TN Display HD+ matt 60Hz",
      "url": "https://www.ipc-computer.eu/laptop-spare-parts/displays/display-mj154-32733719/nup",
      "availability": "Out of stock EOL (End of Life) What does EOL mean?",
      "stock": "Out of stock",
      "isEol": true,
      "page": 681,
      "pageUrl": "https://www.ipc-computer.eu/laptop-spare-parts/displays?page=681"
    },
    {
      "title": "N154I3-L02 Chi Mei TN Display WXGA matt 60Hz",
      "url": "https://www.ipc-computer.eu/laptop-spare-parts/displays/display-n154i3-l02-27173557/nup",
      "availability": "Out of stock EOL (End of Life) What does EOL mean?",
      "stock": "Out of stock",
      "isEol": true,
      "page": 681,
      "pageUrl": "https://www.ipc-computer.eu/laptop-spare-parts/displays?page=681"
    },
    {
      "title": "SD10A09793 Lenovo TN Display HD matt 60Hz",
      "url": "https://www.ipc-computer.eu/laptop-spare-parts/displays/display-sd10a09793-47344960",
      "availability": "Out of stock EOL (End of Life) What does EOL mean?",
      "stock": "Out of stock",
      "isEol": true,
      "page": 681,
      "pageUrl": "https://www.ipc-computer.eu/laptop-spare-parts/displays?page=681"
    },
    {
      "title": "B154EW02-V6 AU Optronics TN Display WXGA matt 60Hz",
      "url": "https://www.ipc-computer.eu/laptop-spare-parts/displays/display-b154ew02-v6-27499524/nup",
      "availability": "Out of stock EOL (End of Life) What does EOL mean?",
      "stock": "Out of stock",
      "isEol": true,
      "page": 682,
      "pageUrl": "https://www.ipc-computer.eu/laptop-spare-parts/displays?page=682"
    },
    {
      "title": "B173HW02 V.0 AU Optronics TN Display FHD matt 60Hz",
      "url": "https://www.ipc-computer.eu/laptop-spare-parts/displays/display-b173hw02-v.0-73320303/nup",
      "availability": "Out of stock EOL (End of Life) What does EOL mean?",
      "stock": "Out of stock",
      "isEol": true,
      "page": 682,
      "pageUrl": "https://www.ipc-computer.eu/laptop-spare-parts/displays?page=682"
    },
    {
      "title": "CLAA154WB03A Chungwa TN Display WXGA matt 60Hz",
      "url": "https://www.ipc-computer.eu/laptop-spare-parts/displays/display-claa154wb03a-23671808/nup",
      "availability": "Out of stock EOL (End of Life) What does EOL mean?",
      "stock": "Out of stock",
      "isEol": true,
      "page": 682,
      "pageUrl": "https://www.ipc-computer.eu/laptop-spare-parts/displays?page=682"
    },
    {
      "title": "LP154W01 LG TN Display WXGA matt 60Hz",
      "url": "https://www.ipc-computer.eu/laptop-spare-parts/displays/display-lp154w01-27499597/nup",
      "availability": "Out of stock EOL (End of Life) What does EOL mean?",
      "stock": "Out of stock",
      "isEol": true,
      "page": 682,
      "pageUrl": "https://www.ipc-computer.eu/laptop-spare-parts/displays?page=682"
    },
    {
      "title": "LP154WX4 LG TN Display WXGA matt 60Hz",
      "url": "https://www.ipc-computer.eu/laptop-spare-parts/displays/display-lp154wx4-25928893/nup",
      "availability": "Out of stock EOL (End of Life) What does EOL mean?",
      "stock": "Out of stock",
      "isEol": true,
      "page": 682,
      "pageUrl": "https://www.ipc-computer.eu/laptop-spare-parts/displays?page=682"
    },
    {
      "title": "LTN154BT02 Samsung TN Display WXGA glossy 60Hz",
      "url": "https://www.ipc-computer.eu/laptop-spare-parts/displays/display-ltn154bt02-32733555",
      "availability": "Out of stock EOL (End of Life) What does EOL mean?",
      "stock": "Out of stock",
      "isEol": true,
      "page": 682,
      "pageUrl": "https://www.ipc-computer.eu/laptop-spare-parts/displays?page=682"
    },
    {
      "title": "LTN154X3-L01-0 Samsung TN Display WXGA matt 60Hz",
      "url": "https://www.ipc-computer.eu/laptop-spare-parts/displays/display-ltn154x3-l01-0-27499641/nup",
      "availability": "Out of stock EOL (End of Life) What does EOL mean?",
      "stock": "Out of stock",
      "isEol": true,
      "page": 682,
      "pageUrl": "https://www.ipc-computer.eu/laptop-spare-parts/displays?page=682"
    },
    {
      "title": "LTN154X3-L09 Samsung TN Display WXGA matt 60Hz",
      "url": "https://www.ipc-computer.eu/laptop-spare-parts/displays/display-ltn154x3-l09-18930178/nup",
      "availability": "Out of stock EOL (End of Life) What does EOL mean?",
      "stock": "Out of stock",
      "isEol": true,
      "page": 682,
      "pageUrl": "https://www.ipc-computer.eu/laptop-spare-parts/displays?page=682"
    },
    {
      "title": "N173HGE-L11 Chi Mei TN Display FHD matt 60Hz",
      "url": "https://www.ipc-computer.eu/laptop-spare-parts/displays/display-n173hge-l11-73320412/nup",
      "availability": "Out of stock EOL (End of Life) What does EOL mean?",
      "stock": "Out of stock",
      "isEol": true,
      "page": 682,
      "pageUrl": "https://www.ipc-computer.eu/laptop-spare-parts/displays?page=682"
    },
    {
      "title": "QD15TL01 Quanta TN Display WXGA matt 60Hz",
      "url": "https://www.ipc-computer.eu/laptop-spare-parts/displays/display-qd15tl01-18935475/nup",
      "availability": "Out of stock EOL (End of Life) What does EOL mean?",
      "stock": "Out of stock",
      "isEol": true,
      "page": 682,
      "pageUrl": "https://www.ipc-computer.eu/laptop-spare-parts/displays?page=682"
    },
    {
      "title": "42T0763 Lenovo TN Display HD+ matt 60Hz",
      "url": "https://www.ipc-computer.eu/laptop-spare-parts/displays/display-42t0763-89116817/nup",
      "availability": "Out of stock EOL (End of Life) What does EOL mean?",
      "stock": "Out of stock",
      "isEol": true,
      "page": 683,
      "pageUrl": "https://www.ipc-computer.eu/laptop-spare-parts/displays?page=683"
    },
    {
      "title": "B140RW03 V.1 AU Optronics TN Display HD+ matt 60Hz",
      "url": "https://www.ipc-computer.eu/laptop-spare-parts/displays/display-b140rw03-v.1-32730450/nup",
      "availability": "Out of stock EOL (End of Life) What does EOL mean?",
      "stock": "Out of stock",
      "isEol": true,
      "page": 683,
      "pageUrl": "https://www.ipc-computer.eu/laptop-spare-parts/displays?page=683"
    },
    {
      "title": "B156RW01 V.1 AU Optronics TN Display HD+ matt 60Hz",
      "url": "https://www.ipc-computer.eu/laptop-spare-parts/displays/display-b156rw01-v.1-72404546/nup",
      "availability": "Out of stock EOL (End of Life) What does EOL mean?",
      "stock": "Out of stock",
      "isEol": true,
      "page": 683,
      "pageUrl": "https://www.ipc-computer.eu/laptop-spare-parts/displays?page=683"
    },
    {
      "title": "HN116WX1-100 V3.0 BOE Display glossy",
      "url": "https://www.ipc-computer.eu/laptop-spare-parts/displays/display-hn116wx1-100-v3.0-144666084",
      "availability": "Out of stock EOL (End of Life) What does EOL mean?",
      "stock": "Out of stock",
      "isEol": true,
      "page": 683,
      "pageUrl": "https://www.ipc-computer.eu/laptop-spare-parts/displays?page=683"
    },
    {
      "title": "LP140WD1(TL)(A1) LG TN Display HD+ matt 60Hz",
      "url": "https://www.ipc-computer.eu/laptop-spare-parts/displays/display-lp140wd1-tl-a1-32733356/nup",
      "availability": "Out of stock EOL (End of Life) What does EOL mean?",
      "stock": "Out of stock",
      "isEol": true,
      "page": 683,
      "pageUrl": "https://www.ipc-computer.eu/laptop-spare-parts/displays?page=683"
    },
    {
      "title": "LP156WD1 (TL)(B2) LG TN Display HD+ matt 60Hz",
      "url": "https://www.ipc-computer.eu/laptop-spare-parts/displays/display-lp156wd1-tl-b2-72404604/nup",
      "availability": "Out of stock EOL (End of Life) What does EOL mean?",
      "stock": "Out of stock",
      "isEol": true,
      "page": 683,
      "pageUrl": "https://www.ipc-computer.eu/laptop-spare-parts/displays?page=683"
    },
    {
      "title": "LP156WH2 LG TN Display HD matt 60Hz",
      "url": "https://www.ipc-computer.eu/laptop-spare-parts/displays/display-lp156wh2-69607811",
      "availability": "Out of stock EOL (End of Life) What does EOL mean?",
      "stock": "Out of stock",
      "isEol": true,
      "page": 683,
      "pageUrl": "https://www.ipc-computer.eu/laptop-spare-parts/displays?page=683"
    },
    {
      "title": "LTN156KT02 Samsung TN Display HD+ matt 60Hz",
      "url": "https://www.ipc-computer.eu/laptop-spare-parts/displays/display-ltn156kt02-72404617/nup",
      "availability": "Out of stock EOL (End of Life) What does EOL mean?",
      "stock": "Out of stock",
      "isEol": true,
      "page": 683,
      "pageUrl": "https://www.ipc-computer.eu/laptop-spare-parts/displays?page=683"
    },
    {
      "title": "N156BGE-E11 Chi Mei TN Display HD matt 60Hz",
      "url": "https://www.ipc-computer.eu/laptop-spare-parts/displays/display-n156bge-e11-47344955",
      "availability": "Out of stock EOL (End of Life) What does EOL mean?",
      "stock": "Out of stock",
      "isEol": true,
      "page": 683,
      "pageUrl": "https://www.ipc-computer.eu/laptop-spare-parts/displays?page=683"
    },
    {
      "title": "N184H6-L02 Chi Mei TN Display FHD glossy 60Hz",
      "url": "https://www.ipc-computer.eu/laptop-spare-parts/displays/display-n184h6-l02-32733885/nup",
      "availability": "Out of stock EOL (End of Life) What does EOL mean?",
      "stock": "Out of stock",
      "isEol": true,
      "page": 683,
      "pageUrl": "https://www.ipc-computer.eu/laptop-spare-parts/displays?page=683"
    },
    {
      "title": "18010-17321100 Asus IPS Display matt 120Hz (120Hz / 40-Pin eDP)",
      "url": "https://www.ipc-computer.eu/laptop-spare-parts/displays/display-18010-17321100-97361881",
      "availability": "Out of stock EOL (End of Life) What does EOL mean?",
      "stock": "Out of stock",
      "isEol": true,
      "page": 684,
      "pageUrl": "https://www.ipc-computer.eu/laptop-spare-parts/displays?page=684"
    },
    {
      "title": "5D10G69059 Lenovo original IPS Display RGB matt 60Hz",
      "url": "https://www.ipc-computer.eu/laptop-spare-parts/displays/display-5d10g69059-80226069/nup",
      "availability": "Out of stock EOL (End of Life) What does EOL mean?",
      "stock": "Out of stock",
      "isEol": true,
      "page": 684,
      "pageUrl": "https://www.ipc-computer.eu/laptop-spare-parts/displays?page=684"
    },
    {
      "title": "5D10G74846 Lenovo original IPS Display RGB matt 60Hz",
      "url": "https://www.ipc-computer.eu/laptop-spare-parts/displays/display-5d10g74846-32698741/nup",
      "availability": "Out of stock EOL (End of Life) What does EOL mean?",
      "stock": "Out of stock",
      "isEol": true,
      "page": 684,
      "pageUrl": "https://www.ipc-computer.eu/laptop-spare-parts/displays?page=684"
    },
    {
      "title": "922934-001 HP IPS Display matt 120Hz (120Hz / 40-Pin eDP)",
      "url": "https://www.ipc-computer.eu/laptop-spare-parts/displays/display-922934-001-97361903",
      "availability": "Out of stock EOL (End of Life) What does EOL mean?",
      "stock": "Out of stock",
      "isEol": true,
      "page": 684,
      "pageUrl": "https://www.ipc-computer.eu/laptop-spare-parts/displays?page=684"
    },
    {
      "title": "B156XTN04.0 AU Optronics Display HD glossy",
      "url": "https://www.ipc-computer.eu/laptop-spare-parts/displays/display-b156xtn04.0-101994747/nup",
      "availability": "Out of stock EOL (End of Life) What does EOL mean?",
      "stock": "Out of stock",
      "isEol": true,
      "page": 684,
      "pageUrl": "https://www.ipc-computer.eu/laptop-spare-parts/displays?page=684"
    },
    {
      "title": "B173HAN01.1 (HW:1A) AU Optronics IPS Display matt 120Hz (120Hz / 40-Pin eDP)",
      "url": "https://www.ipc-computer.eu/laptop-spare-parts/displays/display-b173han01.1-hw-1a-121129227",
      "availability": "Out of stock EOL (End of Life) What does EOL mean?",
      "stock": "Out of stock",
      "isEol": true,
      "page": 684,
      "pageUrl": "https://www.ipc-computer.eu/laptop-spare-parts/displays?page=684"
    },
    {
      "title": "B173HAN01.1 HW1A AU Optronics IPS Display matt 120Hz (120Hz / 40-Pin eDP)",
      "url": "https://www.ipc-computer.eu/laptop-spare-parts/displays/display-b173han01.1-hw1a-97361907",
      "availability": "Out of stock EOL (End of Life) What does EOL mean?",
      "stock": "Out of stock",
      "isEol": true,
      "page": 684,
      "pageUrl": "https://www.ipc-computer.eu/laptop-spare-parts/displays?page=684"
    },
    {
      "title": "B173HAN01.4 AU Optronics IPS Display matt 120Hz (120Hz / 40-Pin eDP)",
      "url": "https://www.ipc-computer.eu/laptop-spare-parts/displays/display-b173han01.4-102085015",
      "availability": "Out of stock EOL (End of Life) What does EOL mean?",
      "stock": "Out of stock",
      "isEol": true,
      "page": 684,
      "pageUrl": "https://www.ipc-computer.eu/laptop-spare-parts/displays?page=684"
    },
    {
      "title": "B173HAN01.6 AU Optronics IPS Display matt 120Hz (120Hz / 40-Pin eDP)",
      "url": "https://www.ipc-computer.eu/laptop-spare-parts/displays/display-b173han01.6-102085016",
      "availability": "Out of stock EOL (End of Life) What does EOL mean?",
      "stock": "Out of stock",
      "isEol": true,
      "page": 684,
      "pageUrl": "https://www.ipc-computer.eu/laptop-spare-parts/displays?page=684"
    },
    {
      "title": "CLAA133UA03 CPT Display matt",
      "url": "https://www.ipc-computer.eu/laptop-spare-parts/displays/display-claa133ua03-121137890",
      "availability": "Out of stock EOL (End of Life) What does EOL mean?",
      "stock": "Out of stock",
      "isEol": true,
      "page": 684,
      "pageUrl": "https://www.ipc-computer.eu/laptop-spare-parts/displays?page=684"
    },
    {
      "title": "2DK4K Dell IPS Display UHD matt 60Hz",
      "url": "https://www.ipc-computer.eu/laptop-spare-parts/displays/display-2dk4k-46182052",
      "availability": "Out of stock EOL (End of Life) What does EOL mean?",
      "stock": "Out of stock",
      "isEol": true,
      "page": 685,
      "pageUrl": "https://www.ipc-computer.eu/laptop-spare-parts/displays?page=685"
    },
    {
      "title": "903366-001 HP original IPS Display FHD matt 60Hz",
      "url": "https://www.ipc-computer.eu/laptop-spare-parts/displays/display-903366-001-70091775/nup",
      "availability": "Out of stock EOL (End of Life) What does EOL mean?",
      "stock": "Out of stock",
      "isEol": true,
      "page": 685,
      "pageUrl": "https://www.ipc-computer.eu/laptop-spare-parts/displays?page=685"
    },
    {
      "title": "9B9BATG3KDZZ-ZZ8300 MSI IPS Display FHD matt 60Hz",
      "url": "https://www.ipc-computer.eu/laptop-spare-parts/displays/display-9b9batg3kdzz-zz8300-79966958",
      "availability": "Out of stock EOL (End of Life) What does EOL mean?",
      "stock": "Out of stock",
      "isEol": true,
      "page": 685,
      "pageUrl": "https://www.ipc-computer.eu/laptop-spare-parts/displays?page=685"
    },
    {
      "title": "B173HAN04.7 AU Optronics IPS Display FHD matt 144Hz",
      "url": "https://www.ipc-computer.eu/laptop-spare-parts/displays/display-b173han04.7-121137885",
      "availability": "Out of stock EOL (End of Life) What does EOL mean?",
      "stock": "Out of stock",
      "isEol": true,
      "page": 685,
      "pageUrl": "https://www.ipc-computer.eu/laptop-spare-parts/displays?page=685"
    },
    {
      "title": "KL.15605.004 Acer original Display WXGA glossy",
      "url": "https://www.ipc-computer.eu/laptop-spare-parts/displays/display-kl.15605.004-78447303",
      "availability": "Out of stock EOL (End of Life) What does EOL mean?",
      "stock": "Out of stock",
      "isEol": true,
      "page": 685,
      "pageUrl": "https://www.ipc-computer.eu/laptop-spare-parts/displays?page=685"
    },
    {
      "title": "KL15605004 Acer original Display WXGA glossy",
      "url": "https://www.ipc-computer.eu/laptop-spare-parts/displays/display-kl15605004-78447307",
      "availability": "Out of stock EOL (End of Life) What does EOL mean?",
      "stock": "Out of stock",
      "isEol": true,
      "page": 685,
      "pageUrl": "https://www.ipc-computer.eu/laptop-spare-parts/displays?page=685"
    },
    {
      "title": "LM156LFGL03 Panda TN Display FHD matt 120Hz",
      "url": "https://www.ipc-computer.eu/laptop-spare-parts/displays/display-lm156lfgl03-53438412/nup",
      "availability": "Out of stock EOL (End of Life) What does EOL mean?",
      "stock": "Out of stock",
      "isEol": true,
      "page": 685,
      "pageUrl": "https://www.ipc-computer.eu/laptop-spare-parts/displays?page=685"
    },
    {
      "title": "N140HCE-EN1 Asus IPS Display FHD matt 60Hz",
      "url": "https://www.ipc-computer.eu/laptop-spare-parts/displays/display-n140hce-en1-92071043/nup",
      "availability": "Out of stock EOL (End of Life) What does EOL mean?",
      "stock": "Out of stock",
      "isEol": true,
      "page": 685,
      "pageUrl": "https://www.ipc-computer.eu/laptop-spare-parts/displays?page=685"
    },
    {
      "title": "NV156FHM-N35 BOE IPS Display FHD glossy 60Hz",
      "url": "https://www.ipc-computer.eu/laptop-spare-parts/displays/display-nv156fhm-n35-53612823",
      "availability": "Out of stock EOL (End of Life) What does EOL mean?",
      "stock": "Out of stock",
      "isEol": true,
      "page": 685,
      "pageUrl": "https://www.ipc-computer.eu/laptop-spare-parts/displays?page=685"
    },
    {
      "title": "S1J-7E0A049-B51 MSI original IPS Display FHD matt 144Hz",
      "url": "https://www.ipc-computer.eu/laptop-spare-parts/displays/display-s1j-7e0a049-b51-112653481",
      "availability": "Out of stock EOL (End of Life) What does EOL mean?",
      "stock": "Out of stock",
      "isEol": true,
      "page": 685,
      "pageUrl": "https://www.ipc-computer.eu/laptop-spare-parts/displays?page=685"
    },
    {
      "title": "B140HAN04.2 (HW:3A) AU Optronics IPS Display FHD matt 60Hz",
      "url": "https://www.ipc-computer.eu/laptop-spare-parts/displays/display-b140han04.2-hw-3a-121129208/nup",
      "availability": "Out of stock EOL (End of Life) What does EOL mean?",
      "stock": "Out of stock",
      "isEol": true,
      "page": 686,
      "pageUrl": "https://www.ipc-computer.eu/laptop-spare-parts/displays?page=686"
    },
    {
      "title": "B140HTN02.3 HP original IPS Display FHD matt 60Hz",
      "url": "https://www.ipc-computer.eu/laptop-spare-parts/displays/display-b140htn02.3-104069532",
      "availability": "Out of stock EOL (End of Life) What does EOL mean?",
      "stock": "Out of stock",
      "isEol": true,
      "page": 686,
      "pageUrl": "https://www.ipc-computer.eu/laptop-spare-parts/displays?page=686"
    },
    {
      "title": "L17303-273 HP original IPS Display FHD glossy 60Hz",
      "url": "https://www.ipc-computer.eu/laptop-spare-parts/displays/display-l17303-273-74962015",
      "availability": "Out of stock EOL (End of Life) What does EOL mean?",
      "stock": "Out of stock",
      "isEol": true,
      "page": 686,
      "pageUrl": "https://www.ipc-computer.eu/laptop-spare-parts/displays?page=686"
    },
    {
      "title": "L17303-274 HP original IPS Display FHD glossy 60Hz",
      "url": "https://www.ipc-computer.eu/laptop-spare-parts/displays/display-l17303-274-74962016",
      "availability": "Out of stock EOL (End of Life) What does EOL mean?",
      "stock": "Out of stock",
      "isEol": true,
      "page": 686,
      "pageUrl": "https://www.ipc-computer.eu/laptop-spare-parts/displays?page=686"
    },
    {
      "title": "L61945-001 HP original IPS Display FHD matt 60Hz",
      "url": "https://www.ipc-computer.eu/laptop-spare-parts/displays/display-l61945-001-94773814",
      "availability": "Out of stock EOL (End of Life) What does EOL mean?",
      "stock": "Out of stock",
      "isEol": true,
      "page": 686,
      "pageUrl": "https://www.ipc-computer.eu/laptop-spare-parts/displays?page=686"
    },
    {
      "title": "L80889-Q91 HP original IPS Display FHD matt 60Hz",
      "url": "https://www.ipc-computer.eu/laptop-spare-parts/displays/display-l80889-q91-102975173",
      "availability": "Out of stock EOL (End of Life) What does EOL mean?",
      "stock": "Out of stock",
      "isEol": true,
      "page": 686,
      "pageUrl": "https://www.ipc-computer.eu/laptop-spare-parts/displays?page=686"
    },
    {
      "title": "LM140LF3L03 Panda TN Display HD matt 60Hz",
      "url": "https://www.ipc-computer.eu/laptop-spare-parts/displays/display-lm140lf3l03-121129292",
      "availability": "Out of stock EOL (End of Life) What does EOL mean?",
      "stock": "Out of stock",
      "isEol": true,
      "page": 686,
      "pageUrl": "https://www.ipc-computer.eu/laptop-spare-parts/displays?page=686"
    },
    {
      "title": "M238HCA-L3Z HP original IPS Display FHD glossy 60Hz",
      "url": "https://www.ipc-computer.eu/laptop-spare-parts/displays/display-m238hca-l3z-74962299",
      "availability": "Out of stock EOL (End of Life) What does EOL mean?",
      "stock": "Out of stock",
      "isEol": true,
      "page": 686,
      "pageUrl": "https://www.ipc-computer.eu/laptop-spare-parts/displays?page=686"
    },
    {
      "title": "NV140FHM-N4K V8.0 BOE IPS Display FHD matt 60Hz",
      "url": "https://www.ipc-computer.eu/laptop-spare-parts/displays/display-nv140fhm-n4k-v8.0-76073994",
      "availability": "Out of stock EOL (End of Life) What does EOL mean?",
      "stock": "Out of stock",
      "isEol": true,
      "page": 686,
      "pageUrl": "https://www.ipc-computer.eu/laptop-spare-parts/displays?page=686"
    },
    {
      "title": "NV156FHM-NXA BOE IPS Display FHD matt 144Hz",
      "url": "https://www.ipc-computer.eu/laptop-spare-parts/displays/display-nv156fhm-nxa-150197940",
      "availability": "Out of stock EOL (End of Life) What does EOL mean?",
      "stock": "Out of stock",
      "isEol": true,
      "page": 686,
      "pageUrl": "https://www.ipc-computer.eu/laptop-spare-parts/displays?page=686"
    },
    {
      "title": "B173HAN01.3 AU Optronics IPS Display FHD matt 60Hz",
      "url": "https://www.ipc-computer.eu/laptop-spare-parts/displays/display-b173han01.3-88643737",
      "availability": "Out of stock EOL (End of Life) What does EOL mean?",
      "stock": "Out of stock",
      "isEol": true,
      "page": 687,
      "pageUrl": "https://www.ipc-computer.eu/laptop-spare-parts/displays?page=687"
    },
    {
      "title": "B173HAN04.9 H/W:0A AU Optronics IPS Display FHD matt 144Hz (40Pin)",
      "url": "https://www.ipc-computer.eu/laptop-spare-parts/displays/display-b173han04.9-h-w-0a-99025941",
      "availability": "Out of stock EOL (End of Life) What does EOL mean?",
      "stock": "Out of stock",
      "isEol": true,
      "page": 687,
      "pageUrl": "https://www.ipc-computer.eu/laptop-spare-parts/displays?page=687"
    },
    {
      "title": "HB2231 HP original IPS Display FHD matt 60Hz",
      "url": "https://www.ipc-computer.eu/laptop-spare-parts/displays/display-hb2231-80236625",
      "availability": "Out of stock EOL (End of Life) What does EOL mean?",
      "stock": "Out of stock",
      "isEol": true,
      "page": 687,
      "pageUrl": "https://www.ipc-computer.eu/laptop-spare-parts/displays?page=687"
    },
    {
      "title": "L73065-2D3 HP original IPS Display FHD matt 60Hz",
      "url": "https://www.ipc-computer.eu/laptop-spare-parts/displays/display-l73065-2d3-101303387",
      "availability": "Out of stock EOL (End of Life) What does EOL mean?",
      "stock": "Out of stock",
      "isEol": true,
      "page": 687,
      "pageUrl": "https://www.ipc-computer.eu/laptop-spare-parts/displays?page=687"
    },
    {
      "title": "L73065-3D1 HP original IPS Display FHD matt 60Hz",
      "url": "https://www.ipc-computer.eu/laptop-spare-parts/displays/display-l73065-3d1-84596144",
      "availability": "Out of stock EOL (End of Life) What does EOL mean?",
      "stock": "Out of stock",
      "isEol": true,
      "page": 687,
      "pageUrl": "https://www.ipc-computer.eu/laptop-spare-parts/displays?page=687"
    },
    {
      "title": "LQ140M1JW49 Sharp IPS Display FHD matt 144Hz",
      "url": "https://www.ipc-computer.eu/laptop-spare-parts/displays/display-lq140m1jw49-99087705",
      "availability": "Out of stock EOL (End of Life) What does EOL mean?",
      "stock": "Out of stock",
      "isEol": true,
      "page": 687,
      "pageUrl": "https://www.ipc-computer.eu/laptop-spare-parts/displays?page=687"
    },
    {
      "title": "M02095-391 HP original IPS Display FHD matt 60Hz",
      "url": "https://www.ipc-computer.eu/laptop-spare-parts/displays/display-m02095-391-104069544",
      "availability": "Out of stock EOL (End of Life) What does EOL mean?",
      "stock": "Out of stock",
      "isEol": true,
      "page": 687,
      "pageUrl": "https://www.ipc-computer.eu/laptop-spare-parts/displays?page=687"
    },
    {
      "title": "M05236-001 HP original IPS Display FHD matt 60Hz",
      "url": "https://www.ipc-computer.eu/laptop-spare-parts/displays/display-m05236-001-84596150",
      "availability": "Out of stock EOL (End of Life) What does EOL mean?",
      "stock": "Out of stock",
      "isEol": true,
      "page": 687,
      "pageUrl": "https://www.ipc-computer.eu/laptop-spare-parts/displays?page=687"
    },
    {
      "title": "N43570-001 HP original IPS Display FHD matt 60Hz",
      "url": "https://www.ipc-computer.eu/laptop-spare-parts/displays/display-n43570-001-112668740",
      "availability": "Out of stock EOL (End of Life) What does EOL mean?",
      "stock": "Out of stock",
      "isEol": true,
      "page": 687,
      "pageUrl": "https://www.ipc-computer.eu/laptop-spare-parts/displays?page=687"
    },
    {
      "title": "P04472-001 HP original IPS Display FHD matt 60Hz",
      "url": "https://www.ipc-computer.eu/laptop-spare-parts/displays/display-p04472-001-102982925",
      "availability": "Out of stock EOL (End of Life) What does EOL mean?",
      "stock": "Out of stock",
      "isEol": true,
      "page": 687,
      "pageUrl": "https://www.ipc-computer.eu/laptop-spare-parts/displays?page=687"
    },
    {
      "title": "Asus 18010-15680600 Display",
      "url": "https://www.ipc-computer.eu/laptop-spare-parts/displays/display-18010-15680600-122712497",
      "availability": "Out of stock EOL (End of Life) What does EOL mean?",
      "stock": "Out of stock",
      "isEol": true,
      "page": 688,
      "pageUrl": "https://www.ipc-computer.eu/laptop-spare-parts/displays?page=688"
    },
    {
      "title": "LM140LF1F02 Panda IPS Display FHD matt 144Hz",
      "url": "https://www.ipc-computer.eu/laptop-spare-parts/displays/display-lm140lf1f02-121129291",
      "availability": "Out of stock EOL (End of Life) What does EOL mean?",
      "stock": "Out of stock",
      "isEol": true,
      "page": 688,
      "pageUrl": "https://www.ipc-computer.eu/laptop-spare-parts/displays?page=688"
    },
    {
      "title": "Sharp LQ156M1JW26 Display",
      "url": "https://www.ipc-computer.eu/laptop-spare-parts/displays/display-lq156m1jw26-122712604",
      "availability": "Out of stock EOL (End of Life) What does EOL mean?",
      "stock": "Out of stock",
      "isEol": true,
      "page": 688,
      "pageUrl": "https://www.ipc-computer.eu/laptop-spare-parts/displays?page=688"
    }
  ]
}